{
 "generatedAt": "2026-07-24T04:40:44.299Z",
 "label": "24 Jul, 10:10 IST",
 "markets": {
  "indices": [
   {
    "name": "Sensex",
    "g": "SENSEX:INDEXBOM",
    "price": 76755.05,
    "chg": -715.06,
    "pct": -0.92,
    "spark": [
     77470.11,
     76755.05
    ],
    "fx": false,
    "ok": true,
    "stale": true
   },
   {
    "name": "Nifty 50",
    "g": "NIFTY_50:INDEXNSE",
    "price": 23996.25,
    "chg": -191.45,
    "pct": -0.79,
    "spark": [
     24187.7,
     23996.25
    ],
    "fx": false,
    "ok": true,
    "stale": true
   },
   {
    "name": "Bank Nifty",
    "g": "NIFTY_BANK:INDEXNSE",
    "price": 57126.8,
    "chg": -708.55,
    "pct": -1.23,
    "spark": [
     57835.35,
     57126.8
    ],
    "fx": false,
    "ok": true,
    "stale": true
   },
   {
    "name": "Nifty IT",
    "g": "NIFTY_IT:INDEXNSE",
    "price": 28549.85,
    "chg": -434.55,
    "pct": -1.5,
    "spark": [
     28984.4,
     28549.85
    ],
    "fx": false,
    "ok": true,
    "stale": true
   },
   {
    "name": "USD/INR",
    "g": "USD-INR",
    "price": 96.53,
    "chg": -0.03,
    "pct": -0.03,
    "spark": [
     96.56,
     96.5261
    ],
    "fx": true,
    "ok": true,
    "stale": true
   },
   {
    "name": "Brent $",
    "g": "BZW00:NYMEX",
    "price": 85.7,
    "chg": 0.84,
    "pct": 0.99,
    "spark": [
     84.86,
     85.7
    ],
    "fx": true,
    "ok": true,
    "stale": true
   },
   {
    "name": "Gold $",
    "g": "GCW00:COMEX",
    "price": 4127.4,
    "chg": -24.5,
    "pct": -0.59,
    "spark": [
     4151.9,
     4127.4
    ],
    "fx": true,
    "ok": true,
    "stale": true
   },
   {
    "name": "Silver $",
    "g": "SIW00:COMEX",
    "price": 59.9,
    "chg": -0.4,
    "pct": -0.67,
    "spark": [
     60.3,
     59.9
    ],
    "fx": true,
    "ok": true,
    "stale": true
   }
  ],
  "sectors": [
   {
    "name": "Auto",
    "g": "NIFTY_AUTO:INDEXNSE",
    "price": 27329.65,
    "chg": 49.05,
    "pct": 0.18,
    "spark": [
     27280.6,
     27329.65
    ],
    "fx": false,
    "ok": true,
    "stale": true
   },
   {
    "name": "Bank",
    "g": "NIFTY_BANK:INDEXNSE",
    "price": 57126.8,
    "chg": -708.55,
    "pct": -1.23,
    "spark": [
     57835.35,
     57126.8
    ],
    "fx": false,
    "ok": true,
    "stale": true
   },
   {
    "name": "IT",
    "g": "NIFTY_IT:INDEXNSE",
    "price": 28549.85,
    "chg": -434.55,
    "pct": -1.5,
    "spark": [
     28984.4,
     28549.85
    ],
    "fx": false,
    "ok": true,
    "stale": true
   },
   {
    "name": "Pharma",
    "g": "NIFTY_PHARMA:INDEXNSE",
    "price": 25752.25,
    "chg": -340.6,
    "pct": -1.31,
    "spark": [
     26092.85,
     25752.25
    ],
    "fx": false,
    "ok": true,
    "stale": true
   },
   {
    "name": "FMCG",
    "g": "NIFTY_FMCG:INDEXNSE",
    "price": 49233.8,
    "chg": 316.6,
    "pct": 0.65,
    "spark": [
     48917.2,
     49233.8
    ],
    "fx": false,
    "ok": true,
    "stale": true
   },
   {
    "name": "Energy",
    "g": "NIFTY_ENERGY:INDEXNSE",
    "price": 39435.65,
    "chg": -151.6,
    "pct": -0.38,
    "spark": [
     39587.25,
     39435.65
    ],
    "fx": false,
    "ok": true,
    "stale": true
   },
   {
    "name": "Metal",
    "g": "NIFTY_METAL:INDEXNSE",
    "price": 12562.85,
    "chg": -60.45,
    "pct": -0.48,
    "spark": [
     12623.3,
     12562.85
    ],
    "fx": false,
    "ok": true,
    "stale": true
   },
   {
    "name": "Realty",
    "g": "NIFTY_REALTY:INDEXNSE",
    "price": 903,
    "chg": -24.35,
    "pct": -2.63,
    "spark": [
     927.35,
     903
    ],
    "fx": false,
    "ok": true,
    "stale": true
   }
  ],
  "global": [
   {
    "name": "Dow Jones",
    "g": ".DJI:INDEXDJX",
    "price": 52218.58,
    "chg": -6.06,
    "pct": -0.01,
    "spark": [
     52224.64,
     52218.58
    ],
    "fx": false,
    "ok": true,
    "stale": true
   },
   {
    "name": "Nasdaq",
    "g": ".IXIC:INDEXNASDAQ",
    "price": 25690.9,
    "chg": -146.31,
    "pct": -0.57,
    "spark": [
     25837.21,
     25690.9
    ],
    "fx": false,
    "ok": true,
    "stale": true
   },
   {
    "name": "S&P 500",
    "g": ".INX:INDEXSP",
    "price": 7498.96,
    "chg": -10.24,
    "pct": -0.14,
    "spark": [
     7509.2,
     7498.96
    ],
    "fx": false,
    "ok": true,
    "stale": true
   },
   {
    "name": "Nikkei 225",
    "g": "NI225:INDEXNIKKEI",
    "price": 66795.84,
    "chg": 680.24,
    "pct": 1.03,
    "spark": [
     66115.6,
     66795.84
    ],
    "fx": false,
    "ok": true,
    "stale": true
   },
   {
    "name": "Hang Seng",
    "g": "HSI:INDEXHANGSENG",
    "price": 25106.92,
    "chg": 214.26,
    "pct": 0.86,
    "spark": [
     24892.66,
     25106.92
    ],
    "fx": false,
    "ok": true,
    "stale": true
   },
   {
    "name": "FTSE 100",
    "g": "UKX:INDEXFTSE",
    "price": 10716.97,
    "chg": 131.06,
    "pct": 1.24,
    "spark": [
     10585.91,
     10716.97
    ],
    "fx": false,
    "ok": true,
    "stale": true
   }
  ],
  "vix": {
   "name": "India VIX",
   "g": "INDIA_VIX:INDEXNSE",
   "price": 13.29,
   "chg": 0.69,
   "pct": 5.5,
   "spark": [
    12.6,
    13.29
   ],
   "fx": false,
   "ok": true,
   "stale": true
  },
  "etf": [
   {
    "name": "Nifty BeES",
    "g": "NIFTYBEES:NSE",
    "price": 273.44,
    "chg": -1.69,
    "pct": -0.61,
    "spark": [
     275.13,
     273.44
    ],
    "fx": false,
    "ok": true,
    "stale": true
   },
   {
    "name": "Bank BeES",
    "g": "BANKBEES:NSE",
    "price": 592.68,
    "chg": -6.87,
    "pct": -1.15,
    "spark": [
     599.55,
     592.68
    ],
    "fx": false,
    "ok": true,
    "stale": true
   },
   {
    "name": "Nifty Next 50",
    "g": "JUNIORBEES:NSE",
    "price": 778.56,
    "chg": -5.87,
    "pct": -0.75,
    "spark": [
     784.43,
     778.56
    ],
    "fx": false,
    "ok": true,
    "stale": true
   },
   {
    "name": "Gold BeES",
    "g": "GOLDBEES:NSE",
    "price": 119.12,
    "chg": 1.39,
    "pct": 1.18,
    "spark": [
     117.73,
     119.12
    ],
    "fx": false,
    "ok": true,
    "stale": true
   },
   {
    "name": "Silver BeES",
    "g": "SILVERBEES:NSE",
    "price": 212.9,
    "chg": 0.67,
    "pct": 0.32,
    "spark": [
     212.23,
     212.9
    ],
    "fx": false,
    "ok": true,
    "stale": true
   },
   {
    "name": "Nasdaq 100",
    "g": "MON100:NSE",
    "price": 323.44,
    "chg": 0.63,
    "pct": 0.2,
    "spark": [
     322.81,
     323.44
    ],
    "fx": false,
    "ok": true,
    "stale": true
   }
  ],
  "mf": [
   {
    "name": "UTI Nifty 50 Index",
    "cat": "Index",
    "nav": 167.79,
    "pct": -0.53,
    "date": "23-07-2026",
    "ok": true
   },
   {
    "name": "Parag Parikh Flexi Cap",
    "cat": "Flexi Cap",
    "nav": 89.8,
    "pct": -0.65,
    "date": "23-07-2026",
    "ok": true
   },
   {
    "name": "SBI Large Cap",
    "cat": "Large Cap",
    "nav": 103.19,
    "pct": -0.45,
    "date": "23-07-2026",
    "ok": true
   },
   {
    "name": "HDFC Mid Cap",
    "cat": "Mid Cap",
    "nav": 226.9,
    "pct": -0.75,
    "date": "23-07-2026",
    "ok": true
   },
   {
    "name": "Axis Small Cap",
    "cat": "Small Cap",
    "nav": 130.52,
    "pct": -0.93,
    "date": "23-07-2026",
    "ok": true
   },
   {
    "name": "Axis ELSS Tax Saver",
    "cat": "ELSS · 80C",
    "nav": 108.59,
    "pct": -0.59,
    "date": "23-07-2026",
    "ok": true
   }
  ],
  "watchlist": [
   {
    "name": "Reliance",
    "g": "RELIANCE:NSE",
    "price": 1284,
    "chg": -19.7,
    "pct": -1.51,
    "spark": [
     1303.7,
     1284
    ],
    "fx": false,
    "ok": true,
    "pe": 23.3,
    "stale": true
   },
   {
    "name": "TCS",
    "g": "TCS:NSE",
    "price": 2207,
    "chg": -14.1,
    "pct": -0.63,
    "spark": [
     2221.1,
     2207
    ],
    "fx": false,
    "ok": true,
    "pe": 16,
    "stale": true
   },
   {
    "name": "HDFC Bank",
    "g": "HDFCBANK:NSE",
    "price": 753.9,
    "chg": -7.55,
    "pct": -0.99,
    "spark": [
     761.45,
     753.9
    ],
    "fx": false,
    "ok": true,
    "pe": 14.7,
    "stale": true
   },
   {
    "name": "Infosys",
    "g": "INFY:NSE",
    "price": 1052,
    "chg": -21.5,
    "pct": -2,
    "spark": [
     1073.5,
     1052
    ],
    "fx": false,
    "ok": true,
    "pe": 14.7,
    "stale": true
   },
   {
    "name": "ICICI Bank",
    "g": "ICICIBANK:NSE",
    "price": 1439.7,
    "chg": -23.4,
    "pct": -1.6,
    "spark": [
     1463.1,
     1439.7
    ],
    "fx": false,
    "ok": true,
    "pe": 18.6,
    "stale": true
   },
   {
    "name": "SBI",
    "g": "SBIN:NSE",
    "price": 1025,
    "chg": -19.4,
    "pct": -1.86,
    "spark": [
     1044.4,
     1025
    ],
    "fx": false,
    "ok": true,
    "pe": 11.2,
    "stale": true
   },
   {
    "name": "Bharti Airtel",
    "g": "BHARTIARTL:NSE",
    "price": 1948,
    "chg": -0.4,
    "pct": -0.02,
    "spark": [
     1948.4,
     1948
    ],
    "fx": false,
    "ok": true,
    "pe": 43.9,
    "stale": true
   },
   {
    "name": "L&T",
    "g": "LT:NSE",
    "price": 3818,
    "chg": -28.6,
    "pct": -0.74,
    "spark": [
     3846.6,
     3818
    ],
    "fx": false,
    "ok": true,
    "pe": 32.7,
    "stale": true
   },
   {
    "name": "Tata Motors",
    "g": "TMPV:NSE",
    "price": 327.75,
    "chg": -6.05,
    "pct": -1.81,
    "spark": [
     333.8,
     327.75
    ],
    "fx": false,
    "ok": true,
    "stale": true
   },
   {
    "name": "M&M",
    "g": "M%26M:NSE",
    "price": 3173.4,
    "chg": -28.3,
    "pct": -0.88,
    "spark": [
     3201.7,
     3173.4
    ],
    "fx": false,
    "ok": true,
    "pe": 20.8,
    "stale": true
   },
   {
    "name": "Maruti Suzuki",
    "g": "MARUTI:NSE",
    "price": 13545,
    "chg": -52,
    "pct": -0.38,
    "spark": [
     13597,
     13545
    ],
    "fx": false,
    "ok": true,
    "pe": 29,
    "stale": true
   },
   {
    "name": "ITC",
    "g": "ITC:NSE",
    "price": 280.8,
    "chg": -0.2,
    "pct": -0.07,
    "spark": [
     281,
     280.8
    ],
    "fx": false,
    "ok": true,
    "pe": 17,
    "stale": true
   },
   {
    "name": "HUL",
    "g": "HINDUNILVR:NSE",
    "price": 2157,
    "chg": 14.5,
    "pct": 0.68,
    "spark": [
     2142.5,
     2157
    ],
    "fx": false,
    "ok": true,
    "pe": 47.7,
    "stale": true
   },
   {
    "name": "Sun Pharma",
    "g": "SUNPHARMA:NSE",
    "price": 1944,
    "chg": -17.9,
    "pct": -0.91,
    "spark": [
     1961.9,
     1944
    ],
    "fx": false,
    "ok": true,
    "pe": 42,
    "stale": true
   },
   {
    "name": "Bajaj Finance",
    "g": "BAJFINANCE:NSE",
    "price": 1056.1,
    "chg": -13.1,
    "pct": -1.23,
    "spark": [
     1069.2,
     1056.1
    ],
    "fx": false,
    "ok": true,
    "pe": 34.6,
    "stale": true
   },
   {
    "name": "Adani Ent",
    "g": "ADANIENT:NSE",
    "price": 3148,
    "chg": -34.7,
    "pct": -1.09,
    "spark": [
     3182.7,
     3148
    ],
    "fx": false,
    "ok": true,
    "pe": 42.3,
    "stale": true
   }
  ],
  "gainers": [
   {
    "name": "HUL",
    "g": "HINDUNILVR:NSE",
    "price": 2157,
    "chg": 14.5,
    "pct": 0.68,
    "spark": [
     2142.5,
     2157
    ],
    "fx": false,
    "ok": true,
    "pe": 47.7,
    "stale": true
   }
  ],
  "losers": [
   {
    "name": "Infosys",
    "g": "INFY:NSE",
    "price": 1052,
    "chg": -21.5,
    "pct": -2,
    "spark": [
     1073.5,
     1052
    ],
    "fx": false,
    "ok": true,
    "pe": 14.7,
    "stale": true
   },
   {
    "name": "SBI",
    "g": "SBIN:NSE",
    "price": 1025,
    "chg": -19.4,
    "pct": -1.86,
    "spark": [
     1044.4,
     1025
    ],
    "fx": false,
    "ok": true,
    "pe": 11.2,
    "stale": true
   },
   {
    "name": "Tata Motors",
    "g": "TMPV:NSE",
    "price": 327.75,
    "chg": -6.05,
    "pct": -1.81,
    "spark": [
     333.8,
     327.75
    ],
    "fx": false,
    "ok": true,
    "stale": true
   },
   {
    "name": "ICICI Bank",
    "g": "ICICIBANK:NSE",
    "price": 1439.7,
    "chg": -23.4,
    "pct": -1.6,
    "spark": [
     1463.1,
     1439.7
    ],
    "fx": false,
    "ok": true,
    "pe": 18.6,
    "stale": true
   },
   {
    "name": "Reliance",
    "g": "RELIANCE:NSE",
    "price": 1284,
    "chg": -19.7,
    "pct": -1.51,
    "spark": [
     1303.7,
     1284
    ],
    "fx": false,
    "ok": true,
    "pe": 23.3,
    "stale": true
   }
  ],
  "breadth": {
   "up": 1,
   "total": 16
  },
  "trending": false,
  "ipo": [
   {
    "title": "Indo-MIM IPO: GMP Signals 34% Listing Premium; Rs 3,810-Crore Issue Enters Second Day",
    "url": "https://news.google.com/rss/articles/CBMitAFBVV95cUxQZUZpT0pMMWxNWmtuY0w2TUF1LVlVN2Z6YUdlcGNjSVRlMmxzLXV0QVJhME43RkRRRVVfa0V1NFh3b05FMlR4VDBLdHJBRDd3dy1BOVloMGVsQjkzM0RJVGF4ZVZPRk5XaWF1UE4yblE5OUhucHpqWEg4bDI5N3Npd3ZiQm9IdHEwcU1NcmNmYWZmUm1YY2I1anQ5RW5fR0I4dHI4TWRYYmwycWVuTnVFTDc0bnTSAbwBQVVfeXFMTWpyaVp6alhkanJQbjhfaV8waHR2YjNrYzQ1dll0ZHdEaG1kb2Z1eEpBd1NaTlozVGhPUFhlNW9qeUNFZEd2ZWRTLV95c1g2N2VUSjlCdzdqeXZZeFp4TzlOMmcxQjV2ai1jam5zSklqOWFxVmo0TFZuM2dtcmFCMXlwZklkTERTemxOT1NuYTZCWTdTdTZYU2x1Vl9tRTlWVU9BYlZfTDdHOHMzWVRfX01EQzViUG9YT3RXa0c?oc=5",
    "src": "NDTV Profit",
    "at": "24 Jul, 09:27"
   },
   {
    "title": "Xtranet Technologies IPO Day 2: Issue subscribed 1.11x so far. GMP hints 6% listing gain. Apply or avoid?",
    "url": "https://news.google.com/rss/articles/CBMi_gFBVV95cUxOUUhEYVFCMDRZalU0LVFudGI3MDU0UmwzanRoeU5GaWswbkJxaWxhSldZOFNKZ3RBM1dDTVQwWVkyUkRTRnREeGNZd0EtTFdXZEN2T1k5V2kwblo2SHFQRFg4M3pSTFBSMS1mMGxHbGJTLW9LOFpTT0d0dnY0M2stUC1JMWNQX0NvY2ozNmJGQ2kyaUxac2NYbmhXcGJiSk8wZzFfQ1M0VTcxVjdoTHBLX2lOZDVLZmh6Q00xS0tEZEpRazRUdnBQMC1CUGQ5Y1pqT2Qyd1NKYk4zSXZGTy1JaUZvYXl6Q3N4T3lGb1dSeEZremZtVzlxTERCY3dNUdIBgwJBVV95cUxOZHkzM1NwbldESWpYWXJ4b3VCc0pkWVhlTWZiZHIzUVJnc2xLZ2pFNzNkR0lVWG5nREE1NEJvdEZoQk9mT2xJdGRsbXFuY1ltTnRCbThwWUk2WW83TGtlbkdkOHNHcGViNU5sb0tVNEdYSlZFN0s2UjBQYWdCLWh3eGpjUDdCV0ZvdnozcVRWQWZIVE93ZkpfeDVRZTZBZzBxcV8wMlU1X3JGVmNhOE9SOE1RdDZObmp1eUl2LUg1elBXdklpNlNueWpWcWxrdlJkNldMSkV3cGtER0ZqdGxfZDdXMmE0dkQyWFlyVDRDQTctVml6ME1aTS1TWGJoMG5iSTg0?oc=5",
    "src": "livemint.com",
    "at": "24 Jul, 08:45",
    "f": {
     "sub": "1.11x subscribed"
    }
   },
   {
    "title": "Cube Highways Trust InvIT IPO GMP, Grey Market Premium Today",
    "url": "https://news.google.com/rss/articles/CBMif0FVX3lxTE9yeTZKR19HQjQzc0pWd2ZrbG1rTHFFRnRSWHlrczhtUHp5S3kzUWlkQ3ZqcjBWU05tMkZKUmo2S1dEbmxVQmtwWi1CTzkzTkpWS3c2S0MyVmk3SFYzMFI3WkVnZ1h1c3F2cTVlMGo0VWVjTzhhSzNuZ3ZOenlFZ0E?oc=5",
    "src": "IPO Watch",
    "at": "24 Jul, 09:35"
   },
   {
    "title": "Xtranet Technologies IPO Opens Today: Price Band, GMP Outlook, Dates, Financials & Review",
    "url": "https://news.google.com/rss/articles/CBMivwFBVV95cUxNOEZzRTNLbXd1amtCUXdJMjdHbzJ0YV9DVFZaZy1JU3lSVHZZTkxNaEFtbk5zbmliYjdpNGJNWnhQRUlYcVpMZ0dLaFdmZlBIdUZMVng2c2U3a2NFZEFBY1B5UmVOa0FMaU1JYXI1a01zTWdpc2o5dkRMT090NHZpS29ncUFTbFk4a3FGNmtYaFIzcXZENVl0bm5CU2RhWXF4THlCY0EwV19OTDlpLWpkMGZFLWtUWS1hUXk2VEpQWQ?oc=5",
    "src": "India Infoline",
    "at": "23 Jul, 11:40"
   },
   {
    "title": "Poojaa Precision Engg. IPO Date, Price Band, GMP, Subscription & Allotment",
    "url": "https://news.google.com/rss/articles/CBMia0FVX3lxTE9ITThhR2ZIcGJOSVJqMkVOai1EWjVzVkthZnZWVnUtcGVmc3V2dm5jaWlKNmVlbWpYV240RVFsVTFVaTVsNnY1ZzhidEFpUDJ4WXFfblJYenBpNXVqeEFWZEl0bG1zaTlDWTFV?oc=5",
    "src": "IndiaIPO",
    "at": "23 Jul, 14:34"
   },
   {
    "title": "Lohia Corp IPO Day 2 Live: GMP signals 9% listing pop. Should you apply?",
    "url": "https://news.google.com/rss/articles/CBMi7gFBVV95cUxQVVJtTFgtYzg5MThvM25lVDlmdnlRbHppQzRoWjlYWXd4RU9mU1Q1WTcwYk1KSzVNam52Qnd4SDFOU09la2hrSVRMajBvcjZ3ckJJdG9laDBaM0c4eEJrUWpZNmNHVDZid3hsRGZrTW90Y0p1X1FuWEdfYlVydGZmMUtRTnI4LWJ1T19oY1R2ckpiZFE3TW1wSXg2d2dTWUJBZTRldThtNmMzb3JpSVNIMlM1SVlYLUFScUYyQ2VaV1lURGxMM09lckdzOHBIQkxoOHh5OFRHbXFfbXJWc21fVjhUWTZFbVJQVks0TE5B0gHzAUFVX3lxTE5kdDJKNVFuVDdVYXNPckpPVzFsNmJvQmRFZ2h3NUY3dmRaeFVnalpTS2NEVjQ5MjhKZXIzQUtjLXFqTFZLRHVmVjdpVmsyeG9iLUdyeHBwbDd5UWw5a0FHX3RMaTFqWGxEbi0tTEpudkx2cUF1WE44anQ2blNnUXljdnhCUkdRa1hKWEFMcmhBWDJ3UGJwMWNraGdhVkpoLXpWSkJMdjZIZDh6X2x0c2tuSy1jZUNOWFVRV3F2UldLamJsUU1SRFdLQW9rMHE3ZUdaU1kzMHpVV1BTSXdvbkMteEU2eTNlbTZDOFdkaXdMV0Q2QQ?oc=5",
    "src": "livemint.com",
    "at": "24 Jul, 09:34"
   },
   {
    "title": "Gulf Lloyds IPO GMP, Grey Market Premium Today",
    "url": "https://news.google.com/rss/articles/CBMibEFVX3lxTFBJWVpGX1V1c3ZQcWFQdFlGT1hkU1BpWVpkVEpudXRVTWpWVk42UGo2amlqSnBjSEQ5Nm9UU01vY0o1bUJhN204OHVRMmk2dC1JZXdOUlVaODRkWmtISTgtNzR4RUFienVaUElWQg?oc=5",
    "src": "IPO Watch",
    "at": "24 Jul, 00:14"
   },
   {
    "title": "Lohia Corp IPO subscribed 5% so far on opening day; check price band, GMP and other key details",
    "url": "https://news.google.com/rss/articles/CBMi6AFBVV95cUxPVFAzN0xyNm4ybjBFYUtZZ3FyVXlYY1d3ZnNCQlN4TTdHT0FzMHVrQ29KMEFzYVdhNG5Yc3FnLUw3U1hsck43eUlzRThHZ21HekpGZ1dOeDBkaGpEXzMzNm9fZ3JKb0RHa05YMUpIcU9BR1dMRE1Zb2xldG1qSVZzUjFvaDR3cDZUdTkwTnJpSWZWcmJMT0hHSno1OXNFVVQwS3RUSEhROUpLZkkwc2FjRlNEbzZ5QTZZQVBKNkVDNG5HNEMtYjFTQVdDbDdXM05Fc0hHRzcyeDZjUWtrUE9CeVIybFgzRnJX0gHuAUFVX3lxTE1va1ZVYkt5V2hoVi1TdVVpTktOSUhEeFAtYkd1RmRZNEtfUTRHMTZtR2hWQXBHelFZTmhONWZaelI1bW10ajk5UUZQeDhPLURacHVnaXo4eXhKRHFUbmZ0dzhvYjV1SV9Mb3N6cVNwMUVTcmt0ajNXd3pLU1VPNG1COW1UWkhid3h6QS1zcE9WNmN3UnNERzV2aEwwajZYNWxRQXVYczA2UGJYWVZUcU8zbllrM3BtaDhLUFpKY1gyZXBHeFJYRWVBNWdXR3RmWVRrQzlSZTZORVJuMkZtTmJSUXdJMzJpN0xLUy1wQkE?oc=5",
    "src": "Moneycontrol.com",
    "at": "23 Jul, 11:27"
   },
   {
    "title": "Caliber Mining IPO GMP, Grey Market Premium Today",
    "url": "https://news.google.com/rss/articles/CBMicEFVX3lxTE5XbTNUZXh4V3hEYnFNVVZDdy1hRTBYc2dpWFVzOXlVZXNwSHMwUWVzQlNqZUtNNkc5YXpkNXM3d09MSnowNFJSeGdBaHhFWUpXbTFxb00wVEtVZVJOcFJXTzdJMzc3YlZVMEtDMzBIQUw?oc=5",
    "src": "IPO Watch",
    "at": "24 Jul, 08:24"
   },
   {
    "title": "Manipal Hospitals IPO sets price band at ₹560 to ₹590 per share; check lot size and key dates",
    "url": "https://news.google.com/rss/articles/CBMi3wFBVV95cUxOQW9OUHJvN2lINDNFamwtYmIwOU1ZcXY1VmptTjRBY2RvSlp2X215QW83c3BFT1pIbEtyaXhQWnBXLXhZb0QyNE95X2g5N1h4Ym9zeHAxM00wY2RtQmdELWREUGNITl9EWGd6bVVYZVlVVDkwZUJuM0IwQ09HSGdWUnA2VkxoR0JlbUtDVTJUMkRXa0lGbVkzejJrR2NqT0hLOWRzcHNNUHNScmZkR0t0WXFVSUVZR3N2UFFVRFFQQzJTMlpQMzJaMGpEa2NoVERLczFPenhjTEFhdVNoeFhV?oc=5",
    "src": "Upstox",
    "at": "24 Jul, 08:49",
    "f": {
     "band": "₹560–₹590"
    }
   }
  ],
  "insights": [
   "Breadth: 1/16 stocks up — broadly weak today",
   "Top mover: HUL +0.68%",
   "Weakest: Infosys -2%",
   "Hot sector: FMCG +0.65% · Cold: Realty -2.63%",
   "2/8 sectors green today",
   "Nifty 50 down 0.79% — bearish session",
   "Rich valuations: HUL P/E 47.7",
   "India VIX 13.29 — moderate volatility",
   "Global cues: FTSE 100 +1.24%, Nasdaq -0.57%"
  ],
  "context": [
   "Broad selling today — most large-caps fell. Down days are exactly when disciplined SIP investors keep buying units cheaper.",
   "Money rotated into FMCG and out of Realty. Sector leadership shifts often — chasing last month's hottest sector is a classic beginner trap.",
   "India VIX is low (13.29) — calm, low expected volatility. Calm markets breed complacency; a good time to check your asset allocation, not to chase risk."
  ]
 },
 "news": [
  {
   "tag": "Business",
   "title": "GIFT Nifty crashes 200 pts, signals sharp gap-down opening for Sensex, Nifty as Brent tops $100",
   "url": "https://news.google.com/rss/articles/CBMi7gFBVV95cUxQWkpsalNxN3BJX2pfTGhJczZNWDduRzZfaWc4NXhXQ1pOcnFURDdMUHpXNER2eHZadE93akhhdVFCVUVrUGNnM3psbGxBR0o0LUVOak5WaTRBcFlPMk9jUzNDSkpLNkhEVmhkbEFCWWNBT093dkxScjNSbnpEbUpRc3BHMDFxNEFHRTFUN2hOckU1N3dVTDNPMGs1WkNkdkpJclBEaHFZUktNSnROMVZlSVcwQnFhNnMzTlJwSGJYb0ltc0xSY0JPeGhrUG5wQ3FLMVZ3WllXZTRyYms3b2V0ZkFYYnByX2xLQWRWOTNn0gHzAUFVX3lxTE1WR0VhM2taX2lNTXBoajhNNXk2TmZZUFlHS01xVTM2ZTUySkg0QmZ4MnNnbUwxSmVmanFJcDNSejVwRVNNVF9vRUI2S2drQnZERUctT21XbDQ5bnhrdmdFVzVEWnhaSzFSUEJQdUtWYllXR2Q4c004N1l3a0pZRmJFcGlwclFNVUE3WHJKaF9oU1VUUnNUUkZMUGt4ZHZvUDdWdWNiNWpZZFJrdmtyRWw4UWYzdlkzcmw4SEJ1d0RWUWlSMFd4enJ6SkhUQ0VOYXlUcE55aTZBNjJDcnpieldWM3BuUndTRkhZMDdIR01kdnFFUQ?oc=5",
   "src": "Moneycontrol.com",
   "at": "24 Jul, 08:11"
  },
  {
   "tag": "Share Market",
   "title": "Sensex, Nifty surged nearly 4% following announcement of ceasefire agreement between Washington and Tehran",
   "url": "https://news.google.com/rss/articles/CBMiiAFBVV95cUxPLVZNa0dvVmRZbGMwalItYmxmSzh4Q1d2NUZUWDlfWTloTjgyRzk2YjBYclMycDhOWE5PR3lBWG1mbXUxaUd3eHgzTF9XMjlqcEdWZU9qN3oyTXVJWThuM3I5ZVNibk9YaVM0bHFOY3RfV0t2Z2ZoZzlKR3NLbFVma2dtcTgwd00t?oc=5",
   "src": "News On AIR",
   "at": "24 Jul, 04:29"
  },
  {
   "tag": "Share Market",
   "title": "Sensex crashes 700 points, Nifty 50 drops below 23,650; investors lose ₹4 lakh crore. Why is market falling? Explained",
   "url": "https://news.google.com/rss/articles/CBMikAJBVV95cUxPU2huTmdtQ3RtQmtXUkxXcGtIbEN0REljS3JtaVJvSWxlenFDX1BadWc5aTEtQTN4NWNwNWgwVTZkLUZmS3JHZlF4eDBISTR0enJtUFhvT0xkMnFHRWFwdzZDOXNHM2tZb0k1Mno3MGVCeGpGQjRoQjlzbFZuYjc5TnVSR0I1V185enBVZkVxT2NrZ3dxV3I1cmlaM2hTV0FRSHRRYmhPR3B6QzA3Slh5ZjdJS3lPTXNUU3lmY2tuWXJEYXo5cXhEV1hrNTVJSmt2a3dtUHB3empxOVk1cVJzbngyNVBiMFlWMHpSZGxmeDFjeWR0Y1BSRVI2Rnl5QW5nbmoxSGN5TkJHcUhEXzM4V9IBlgJBVV95cUxQN0RyYjkyTmFFT2RSYzlza0hycjdqVWllZUFDTTZCU20yaUp0UkRQN2xhRERIWlNKazF0ZFJXU1lsSzJUbEVJWkpoVmlYTk5XeGtJbzlsWngzSnM1cXpEMEJoMTZVVW5mRWVmMU9yY2RscW84UDJGQ0lqOGhLMGdtME9xSG0yZzBEVEVjbGlLUl9RdWI1eW9HYWh6LVBGOEQ1RlpwWWRMY0tYakpjMXo4dzB1cE5uWFpzV2wyUVFFUzNkckJ2NXU5MTFUdkhZRWFPNXFxTzNHemVSV3A1T2Q0Zm1aSTVCMnJ2RTVSa2xzLXhrWFhLaU9ueGxoMktvU19MMmtza3VBSmdxZ2c1NC1XNWtBaEdmQQ?oc=5",
   "src": "livemint.com",
   "at": "24 Jul, 09:19"
  },
  {
   "tag": "Sports",
   "title": "Sooryavanshi, Mayank help India end T20I losing streak",
   "url": "https://news.google.com/rss/articles/CBMirwFBVV95cUxPNFdOOE1oVkNqSUNuMFhPWkdvelotdFMzOTFLa2Z5aUlhdVdUbEF2MU9uTUxUaXM0djBESV9VMXZ1OVVGU0lMMXotVEVRVG8xUW5YR2JObkk0YXozZUJGa3JfQUljX3IzMEh5cXB3Rko2MTMtM0tHSEpNanZvNmlnYmJoU2pzS0hsaXlya09jYV9vMHFBdUFCZ2JQVmNnMVVROFBQbWNvbzZxTFN3S1RR?oc=5",
   "src": "Cricinfo",
   "at": "24 Jul, 10:00"
  },
  {
   "tag": "Tech",
   "title": "Samsung Galaxy Fold8 series and Z Flip8 coverage wrap-up - GSMArena.com news",
   "url": "https://news.google.com/rss/articles/CBMimwFBVV95cUxNVFBTTk5WOF8xRTJHX29udmROREFTM2NJTGdqX0hiN19FUFFXRWZ4VFV0RXNLZ0drUUM1aUh2cVJ0M29LZFdEaDRJeGFFaENrRmdVQ0VHcWhnWEQ4TExvWU11a29rdERrd1RubS1fWm1kdkpRUFFLcnhDMGxHbnEyWGd0R2QyMmo3Y0kzZzljUlFjZnZfdWdBTUhyWdIBlwFBVV95cUxOV2wwZHYtcjAySXg0RzVXVUttV295MDY0Ml91bFpxQkx1ektIMVJqaGxZTjVhUFYwMnh5QkFqVy1EOVh4WXVoSTdJVmlnZlduVzVFT253ak5sM05lUnh0WlFZOE1UQnF6NWVKQ0JyajNZSEJieXpTUFlrbFdZOE83WmZ5YVROQmFyckhxSGhzaml3Mm9zV3JR?oc=5",
   "src": "GSMArena.com",
   "at": "23 Jul, 21:17"
  },
  {
   "tag": "AI",
   "title": "Artificial Intelligence and the new gateway for Chinese Influence",
   "url": "https://news.google.com/rss/articles/CBMimAFBVV95cUxQYmxuUkpKNlJ6VmM0N2c3TXhnWFF6dWZ6Z0s2SGJaQ3A3dnFkT1p0QzhHb3lPMnkxQm5fWnBjODhHcWdzWVlNNmc0aXRnSEVRLTI4YzE4aEtabHR6UWpxTFo2cjc3ZV9CaEVValJUMFF0bnV0WGJES2RKNUpsbDdYcGtHaEY2NWwwMnp1WlJoRDFMMkVjbFk4Yw?oc=5",
   "src": "Decode39",
   "at": "24 Jul, 01:24"
  },
  {
   "tag": "AI",
   "title": "UNESCO and LG AI Research Launch Global MOOC on the Ethics of AI",
   "url": "https://news.google.com/rss/articles/CBMikwFBVV95cUxOS256RTBsT0lHUWR3QkxoMml2U1QyUS1SVS1mQXlZd3ZaUldGSWwyMGxhdHYxYTFycC1ET19Xc1RvaTg0X2JOV1NxVUN4QXhBNHZWY3ppQ1o5cVhBZ1FPcGQ2UXljTWFjVW9zN05DdUZPUXU3X0tkMHN2NXM0a0NJWE45bVdTbXp4U3ZLenFZNTVMNzQ?oc=5",
   "src": "UNESCO",
   "at": "23 Jul, 23:03"
  },
  {
   "tag": "Economy",
   "title": "RBI keeps repo rate unchanged; Projects India’s real GDP growth for current fiscal at 6.9%",
   "url": "https://news.google.com/rss/articles/CBMivgFBVV95cUxOTGFSNzg0VzlJdnMwYWh2TzliX3libXhnd0pFajdsbW05R3dZU3Y5V3BjRU5uV2Q0aDVOZWZNX3dDdHpvNXpGOXRTQlNnQVRScklzNU5QdjVmV2YzOWlFVWZXMXFSZWxscFJIdFY0UHhleHZreWhkRmhqNGpCeTBYTVlpZ3AxcFN5X0h6SkFqSHJzSTBhWER6N1lkQXB3cnlLRXU4TF95ZjNWdC01XzBkTm0zOGN3RmpXc1lQSkdR?oc=5",
   "src": "News On AIR",
   "at": "23 Jul, 23:59"
  },
  {
   "tag": "Politics",
   "title": "E20 Clean Fuel, No Plan To Return To 'Pure' Petrol: Centre In Parliament",
   "url": "https://news.google.com/rss/articles/CBMirgFBVV95cUxNUkdDZnFKYWJKYVlMNFU2aG1qR0Vrc2ROSUNwQTNIM2pMaTNKb1VSbnc2bDdQSkpPeUdsQTFWWXdVTmFsUTRqbEJ5MGxXc0pCWXdlR1JBb1dNeG1rQ0VaSXFKQi0zaGo5V3dGc290QUZqODRNZWdURWl4N1U3RjF3bmdDMURzdlZVd3Z2X3BhMWtROTIyY0dSX21ESjVtR0gxbDlDLVc3c0xKOVB4TEHSAbYBQVVfeXFMTUlKalJpMmZyODRHVFF5NE54RW5HODlWdjZKS0JZTENYTWc1YlFZczEydU9DYkhadk5ucThPQTdEUXdoUnlkWHpuaHNQUGhUcHRhUnRaRlRhM0t3NHd3QUM2QWo1dmZvdjZ6MEIwMGVFR2pEZG9BZThfeWVwV3FjSG9hUFBIVjNRVE5BNUJVYnNmRU1BTFZZaGRyNVNTaU9HMlVWWDVCcEx4dTVGeE1WeU8wYTNHY3c?oc=5",
   "src": "NDTV",
   "at": "23 Jul, 16:46"
  },
  {
   "tag": "Jobs",
   "title": "Oracle Layoffs 2026: Tech Giant Cuts 21,000 Jobs Worldwide as AI Reshapes Workforce; Indian Employees in Focus",
   "url": "https://news.google.com/rss/articles/CBMi3AFBVV95cUxOX0txa3l0Uk16TzQ0NVcxbVBod3ZfSk5FQU9HaG9FNWd2VTd3VGxaNHJsTmVlVHh6VnhWQWdOeFZmSER6dFhVY3RDUGVZQkhuR2pTelVUMXFqbUpBYWZSMlFpU0lzcFRUNzJWQWtTMjRFbFlMZmpjTnlDLTRwcEd5aUo0VTh4OXZlTG1uZC1wR01La1c3R09tRDQ1MGEzTlpYV3ZwVmRuZG1XVWZIVVpkdjFRdGpWR1IxSjN6U1ExQ09tQl9uYmRvWjRwbEs2Uk9CVUlSNVFXWk4yUmU3?oc=5",
   "src": "Goodreturns",
   "at": "24 Jul, 07:32"
  },
  {
   "tag": "Crime",
   "title": "India signs Mutual Legal Assistance Agreement on Criminal Matters with Nepal",
   "url": "https://news.google.com/rss/articles/CBMipAFBVV95cUxPcGtCeDhiUEtLTnVJd3BPZnVOdno4aHhXSGNiOFpaYndTQzNwQ0tTeDYwYWhfUWJNNDVMVnRHUjJ1eXY3MnJ6WVRESWsyUFFhYkdJc0hpc19STC1manRtWkVKSElKaWIzRkN3Y3ZDYXQ4SWt5c0daOF9xQm8zY29RZWdLQ3AxSy0tTFJNRnliRnNfdHBOU3Rhb1otVVZLSDBONjJ0Mg?oc=5",
   "src": "News On AIR",
   "at": "24 Jul, 04:02"
  },
  {
   "tag": "World",
   "title": "US Strikes Iran As Tensions Escalate Over Shipping Routes In Hormuz",
   "url": "https://news.google.com/rss/articles/CBMiugFBVV95cUxPUXBOWnNuc3RUUEZKVGNUaFc5bGlpOGR2NXk3TTYxUTk5Yk12T1c5cDFuYjRQbm1JRGZrSTZHVTNVSXYzdFlCWExvd0xvSzRCQ0JXMXF2c2JGMFFFMTE5YWxidVpaM3NMZVBUNS1SRm1YSDAzLVEzZE9ucTlISWNQQW1iQlpuSy05MzR1ckJjeGVjckoyV3hmNmR4cS1SVzlXV1ItazRBN3FXVlZGTmRSV2FLdU9oaFd4NGfSAcIBQVVfeXFMUFBLWmZQYmd0eUdPMThwSHB5RzNoWDlaSm4tSjZLaFNZN2U1TFptb0ZkTTU4NXBxaDdPZjl4RjdycDdMSGVSSUxPTUFkdXdhRG56ZkhKNVl0MEhOSjhXcXFxMFh3QmJkYWtKYk5pZm5lbFBXLXJmSC10ZmU4N2M0MFlSN2hXVDUyU2hEUVZvTDFzS0tfeHJyaDdQLVhuYWRQdTBjaUJRT1B1dHZOd2c1VWd0RmRSWmJzU3FNb3FWTHBHamc?oc=5",
   "src": "NDTV",
   "at": "24 Jul, 04:59"
  },
  {
   "tag": "For You",
   "title": "The 1.6x problem: Why India’s manufacturing AI spend is outrunning its data",
   "url": "https://news.google.com/rss/articles/CBMiwAFBVV95cUxNSDNmcGVFOTB5bFdXa3F4Tmk1Q1FVZ2twUzM5MnMtdmh0a09UNnNYd3c4MDlVODN2dUlZZmx2T2xadHJuRTlkN0FSMEdwUm04YkZsS3lIUThYYS1faXVtbG91UGJqaFRVZ25qaGVaOXVNdlVzelU1UzREXzNacGE5VEZab21BRkJ3ZXY2dTNmQXAzZjl3NDQwV1dUR1JGcV81eVFsUzZ2amsyUkxpOGoxemprQzhHdFVzUS1KdDR2XzI?oc=5",
   "src": "Express Computer",
   "at": "23 Jul, 16:05"
  }
 ],
 "browse": [
  {
   "tag": "Business",
   "items": [
    {
     "title": "GIFT Nifty crashes 200 pts, signals sharp gap-down opening for Sensex, Nifty as Brent tops $100",
     "url": "https://news.google.com/rss/articles/CBMi7gFBVV95cUxQWkpsalNxN3BJX2pfTGhJczZNWDduRzZfaWc4NXhXQ1pOcnFURDdMUHpXNER2eHZadE93akhhdVFCVUVrUGNnM3psbGxBR0o0LUVOak5WaTRBcFlPMk9jUzNDSkpLNkhEVmhkbEFCWWNBT093dkxScjNSbnpEbUpRc3BHMDFxNEFHRTFUN2hOckU1N3dVTDNPMGs1WkNkdkpJclBEaHFZUktNSnROMVZlSVcwQnFhNnMzTlJwSGJYb0ltc0xSY0JPeGhrUG5wQ3FLMVZ3WllXZTRyYms3b2V0ZkFYYnByX2xLQWRWOTNn0gHzAUFVX3lxTE1WR0VhM2taX2lNTXBoajhNNXk2TmZZUFlHS01xVTM2ZTUySkg0QmZ4MnNnbUwxSmVmanFJcDNSejVwRVNNVF9vRUI2S2drQnZERUctT21XbDQ5bnhrdmdFVzVEWnhaSzFSUEJQdUtWYllXR2Q4c004N1l3a0pZRmJFcGlwclFNVUE3WHJKaF9oU1VUUnNUUkZMUGt4ZHZvUDdWdWNiNWpZZFJrdmtyRWw4UWYzdlkzcmw4SEJ1d0RWUWlSMFd4enJ6SkhUQ0VOYXlUcE55aTZBNjJDcnpieldWM3BuUndTRkhZMDdIR01kdnFFUQ?oc=5",
     "src": "Moneycontrol.com",
     "at": "24 Jul, 08:11"
    },
    {
     "title": "West Asia war updates: International benchmark oil prices cross $100 per barrel",
     "url": "https://news.google.com/rss/articles/CBMiggJBVV95cUxOcVpKeUJtZWwwVlZ2RnFVbU5XZllKRlN3cENNQ1dRdEFGcVdSSzZxRkktTXBBdFM2Xy0yM2JqSDdiUEtjVENQSWVLdFB1TjUwQkxHdUlDd2tNbFV6N011WEJLMjNDWGFnU0ctSTJXd0RyX2ctdmVRUmNjR0tkS2dCUDVBRnZtcmtGNU11MUlyekw0RG1hUFJ1dm5QNkhaclZwV3ktV0NuNndwMEdVSWpBRGhmYmRDbGJoNThWVENXT1Rqd1VnZHRFc0JWaU1oMF82VFoxdUhVLVp0aENJLWNwT2RKcWhKMDRoWUhsNVZJOFBsSFdORG1NUGl4UHZMOWc1WHc?oc=5",
     "src": "The Hindu",
     "at": "24 Jul, 06:57"
    },
    {
     "title": "IndiGo's Rahul Bhatia says ‘massive conflict of interest’ as Adani Group eyes airline venture",
     "url": "https://news.google.com/rss/articles/CBMi8gFBVV95cUxQN25QcEZjZ05qVkJhVTZsR1k5NWptdTBVOHVlQ1hqWENreVVqbGhOeDB0ZFlSNk5ySkZiUDEyaUtqRkJ2UDBMbldnSVNvNkhQaWJPVkozOVQzU1RjQl9MbW41bkNGMnRGM09JZzhPNXh2SW1sVnMxeDYzYkgyRlpBVU1DU21OUmJpZWY3ZE5sV2NHS0lsdFNPamF4MndaV0xtOHlDZ0NfaU0tdk5JRHkxTTVHczBueU1lMlU0RmZUSVUtcTJnTzd6QlNVbENsSUt5ajVESF82ejJyWTBucjNHYThZcXExRnZ0d2U3SmxUODlod9IB9wFBVV95cUxQUTRIMWp6dHg2VlZ1Rml3TnJoTnl6Zi1jNXg1eHIwRkZjZm5nbXdDeHNfR0ZDU1pIMjlRa3ZNWVY1RXdQaTNPSVFxRXVJR0xJc2ZzQUR6TmgzM2ZFS2Rnc0dnTlZ3dGE3anNhSmd0UENvcU9scVVXSGRCcjVBRzJwQ05tWjRBQ3lpVHJ1SEpBeGhPSHdxMUtmcDkxQU5yOEh2Yi1pbjA5M0g3MFNndkFxRTBpMjZrblMwaEhYUnhmRHVSZHVVY0Ruc1RLSHBPTlBHX0lvS0tuUHZYQ0tsYXNqRU1SSG9iN003MXFreUt1NEdJNnFlQ2RV?oc=5",
     "src": "Telegraph India",
     "at": "23 Jul, 19:35"
    },
    {
     "title": "India relaxes e-commerce investment rules for exports in win for Amazon",
     "url": "https://news.google.com/rss/articles/CBMirAFBVV95cUxQUk8xcnpNeU9mY0RLYi1CM3lKdk5xS1ZjcDhhWkJYclJVZmJyUnl4RlBZd0x3ZHlseU5va096WFBLNlhndWtLMFlKZXdfTktqbk1nR09jbWlRSkR3WWRVdUlBaUI0UDJHSURXUnBVdkpRemtNTW1XeUJrbV9HdTdKMlJGTDlIRDhZRVJFMXVhLURnMW5YN1FPNUgzT3RiUGJzOEtWaWl1bU1ENGI0?oc=5",
     "src": "Reuters",
     "at": "23 Jul, 21:36"
    },
    {
     "title": "Shadowfax Technologies block deal launched: Flipkart, Eight Roads, others to sell shares",
     "url": "https://news.google.com/rss/articles/CBMi5AFBVV95cUxOdjVGaGY2c0U0TzNRRlNBYmZ3RDFqeDZ0QmlOekhmUy1jUWd1UWNyYUFabzliNzEwMGFZSVhyb1kzOXRxTGFhMFpMZ3ctdVRvQkN3WjlKZDlpTER4eHpvSWtvWW5oMkNCRTREZzRKYkQ2X2dIQXRkaFFVR0hBR1hGUDdOODVlSGY0ZVcyWTRWWWNRb1R5U3Znb00zMFRFMlJKRHpGZ1owU19CcXl6dVNDMFJ6SFRLaUlJZEZjSy1TZlFPNEVVb3IwRW5oUzA3Sk04V3UtU1NFNEQ4REQzaHhWb2ZTOGzSAeoBQVVfeXFMTUdCYXAwMjFhU3RVek83YVZCRkEtNlpJay1nSHNLRzVYeEtGWUtOYk4wR3B1ZVBDS25aTEFib1QtWjNqYmY3N3V6LVdOYVZuY082eVVSWGYyYXNoa0lSbmpDT2NkZ1hEcldDT3Fnbk9ybzIyVThuemVVQXRsNGVkeGlOd3VOR28zb0d5d1hoeElJa1pQaS1nd1FiOWk1aFBxUWpnM1hHaVV6RWdzckdSUWhNZi1oRVhWT1dEeGNOcXBCUFZnWXExY3ZsLWVuS3ZnTkN5ak5BMllkRkZPRE9HcDItcmthWGlkSnpn?oc=5",
     "src": "Moneycontrol.com",
     "at": "23 Jul, 20:45"
    },
    {
     "title": "Infosys shares get multiple downgrades, price target cuts after Q1 results; Details here",
     "url": "https://news.google.com/rss/articles/CBMi0AFBVV95cUxOUGtIWGt3SXdGdl9CQkRfQVprNGVfRmU5T0RNb0N4MmljcGVmelVqMTJrOThxWVdsUzBuMV9XTndoemczclpveGk0X2xIOVFhck5ac2RQTGJuMDNwQk5vU1ZTeXJBbEwxbFhiVTBKdDhBQXc3THp1a0tHMUlUZ1BmZDI5ekhTSlJyNEgtR2J5V2NQWjlTY19SZVdUamhNR0lmZjJQUURvb3JjYjlacTJKSTZnSU1JcnRQbnFEY1NFenNzZlNYZnhQMGxpdEJVZTNf0gHWAUFVX3lxTE1QSE9EOXdNN2tHdXBaU2V6QWF0a2NicmhsWXozbWdtSHJHWURmWVNyWkNGVGlrSmxOV0I5M2VjenFJcjM2N18xZERDQzlFbjZaQWt5Z0FFeDMzYW9yTDhYM0JRZ0ZIM0tiSmYxcWREN1UtaFplcmRUU3NLbTZJdTZtZTFzcmJtM3ItUk12VWRiQldpYWdkTmh6RFNXZzYtdEY2Ym5yNDQyZi1VYUJiLU1LU1UzRklObF83aXNNWGVEYlg3c2NYc1RQczJQZWpzZnJfZUNsaEE?oc=5",
     "src": "CNBC TV18",
     "at": "24 Jul, 07:54"
    }
   ]
  },
  {
   "tag": "Share Market",
   "items": [
    {
     "title": "Sensex, Nifty surged nearly 4% following announcement of ceasefire agreement between Washington and Tehran",
     "url": "https://news.google.com/rss/articles/CBMiiAFBVV95cUxPLVZNa0dvVmRZbGMwalItYmxmSzh4Q1d2NUZUWDlfWTloTjgyRzk2YjBYclMycDhOWE5PR3lBWG1mbXUxaUd3eHgzTF9XMjlqcEdWZU9qN3oyTXVJWThuM3I5ZVNibk9YaVM0bHFOY3RfV0t2Z2ZoZzlKR3NLbFVma2dtcTgwd00t?oc=5",
     "src": "News On AIR",
     "at": "24 Jul, 04:29"
    },
    {
     "title": "Sensex crashes 700 points, Nifty 50 drops below 23,650; investors lose ₹4 lakh crore. Why is market falling? Explained",
     "url": "https://news.google.com/rss/articles/CBMikAJBVV95cUxPU2huTmdtQ3RtQmtXUkxXcGtIbEN0REljS3JtaVJvSWxlenFDX1BadWc5aTEtQTN4NWNwNWgwVTZkLUZmS3JHZlF4eDBISTR0enJtUFhvT0xkMnFHRWFwdzZDOXNHM2tZb0k1Mno3MGVCeGpGQjRoQjlzbFZuYjc5TnVSR0I1V185enBVZkVxT2NrZ3dxV3I1cmlaM2hTV0FRSHRRYmhPR3B6QzA3Slh5ZjdJS3lPTXNUU3lmY2tuWXJEYXo5cXhEV1hrNTVJSmt2a3dtUHB3empxOVk1cVJzbngyNVBiMFlWMHpSZGxmeDFjeWR0Y1BSRVI2Rnl5QW5nbmoxSGN5TkJHcUhEXzM4V9IBlgJBVV95cUxQN0RyYjkyTmFFT2RSYzlza0hycjdqVWllZUFDTTZCU20yaUp0UkRQN2xhRERIWlNKazF0ZFJXU1lsSzJUbEVJWkpoVmlYTk5XeGtJbzlsWngzSnM1cXpEMEJoMTZVVW5mRWVmMU9yY2RscW84UDJGQ0lqOGhLMGdtME9xSG0yZzBEVEVjbGlLUl9RdWI1eW9HYWh6LVBGOEQ1RlpwWWRMY0tYakpjMXo4dzB1cE5uWFpzV2wyUVFFUzNkckJ2NXU5MTFUdkhZRWFPNXFxTzNHemVSV3A1T2Q0Zm1aSTVCMnJ2RTVSa2xzLXhrWFhLaU9ueGxoMktvU19MMmtza3VBSmdxZ2c1NC1XNWtBaEdmQQ?oc=5",
     "src": "livemint.com",
     "at": "24 Jul, 09:19"
    },
    {
     "title": "Sensex down over 700 points: 3 reasons why the stock market is falling today",
     "url": "https://news.google.com/rss/articles/CBMi-wFBVV95cUxPc0djQk9yX1Q0TU1BTUduQWpoX0JNT1J6VVlFUlJnSzhOcWhXOENtT0x1YVNfTkc3bEFRRWh6VVRpOFlUSVd4bGdQRXVabTJ2WUFtN0lNa0FQbW5oRVM4bC1nTnZsaFFJYTIzSGR4bG9IdVE5LW4talF2b0pqOXhNeXVwYlNuZzZJNnhyRE1RMVpBRlVQdlRMbV9aeWpIQVBuXzdPWEdCaVNQeHFPd2lsZ2tLcDNIOXdDV21RLTlqR2pLZUh1NXNmOHVOOUFTeEIzVW9PSWZreUlsWHVJNEdtNHBNUzBUaGJFckZrZzdXcnFINmFlUTlvTGZtUdIBgAJBVV95cUxQUGxaSW9WVE1oOGwyS2w2OU56VXpIZkp2MzlnTWxSRkszalVNM25lTFNfSjJKbGVOSkV6WDZ4LUVuRUI4OXpySFA3LUh5MDFuMG1JczdkZXNVcXZtV1FDWmNobVhnOUlWZmpobHpyQU14RklMZGczWGdGc0pxM2x3WVd1Y0prQzBEMkNjVldpbjVWU285S2dNamk5Tjh2YjFYS3dFU3pnN0JrcUZuVEJDSEhrTk90M1dhMjJrSDFGajRPSTJwbDVYcXhsQ2xzSHkzbFl3eHpaUG1HTXpidXRRMmNUeDV6UXlfNjRlRlFLNlcyeHB0UUVqMVZNeHM2eExr?oc=5",
     "src": "India Today",
     "at": "24 Jul, 09:42"
    },
    {
     "title": "Why Did Stock Market Crash Today? Investors Lose More Than Rs 3.5 Lakh Crore Within Minutes After Nifty, Sensex Extend Fall For Fifth Day",
     "url": "https://news.google.com/rss/articles/CBMiiwJBVV95cUxQMGVDcEI0UVZ1TUFXdjA5Vmg4UTQyajVyd05HZGpGZXQ3bFhtOWctZ2tMWG5zcDk0VFlWdVc3QWxXdjFlZ0FULTZucXpwZy1rYk9MX3ctOW11eG5CVUVmb0MxYnd3NFdLNmZCcGtmd0hRYnh3alBwVm1yRzdVb21lLW05Wm9ySGFBTW5ZQl9lTWNaS2pnd3dmWXItYTZweGNGd0ZfQTJwd2FQeWkxSlBHZWYwdmlGaV9WZEFVaW9JcmxVeGY2NTRPMW1QT25ObjhoeVh3bjdOZkFBTTVTYmtETXZfOERxUkFQRE9zdG1COFJ0V01NMGhaaDVZZjhHR1Fha0tLYkVOTUVQeVHSAZMCQVVfeXFMT2tDX0JDYTJqSzhveGY2UVdqUlN2VzNIdF9XTGVCbDd5N09SNUE0Sk5VX3dpYWg2N2pIRUltN0JVakpvQXJrNTRXQUhYTUtXYnpIZTJfSFA5d3BOeTdycERnQWVtYWxIMmpIOTFiQmJndUFRQXo5LVhGak15NkNWeGpsM1M0U20za1Z5dVY5MjB3WGJFdWZSbFN6SHVzeGRJazVpQmNaQXh4LU5aS004dFplX1lVMzE3UkRNUS1NanBRRTFkS0Q3aFJQbU5KMWVINmo5cDZLTnVCVWQ4ZXpkZG9oWk5YYjNnZmdjZ1FyNUM0NGlaZTRPRTF1bWEwX0dyNExtXzdHQmZJeXlES3JoZC0wemM?oc=5",
     "src": "NDTV Profit",
     "at": "24 Jul, 09:32"
    },
    {
     "title": "Markets slide as oil goes above USD 100 per barrel amid West Asia war escalation",
     "url": "https://news.google.com/rss/articles/CBMixAFBVV95cUxPUUVvSWptbVZrRTQ5aVRXSDZqTWZvTl95TFhNS2luSzlsdl9SVnVvLUdLUnItSmd4WFJuZGZwaHg5SWJKYVFPMF94MWZWTkpXb2Jid3ZkOGtKbkdQNU1lZ3FTYmdrbVRRazQwZ3E3MkpDNU9lYWk1YXJGYjNwOTJZSl9vdFU1VF9adVJ2NV9qN3FhYUFSMFRPTk5vZGZseGp0LXpFS3I3Y2k3TGpiblJ2SERhWDNMel9QUVg4WjhaX09VcVBY0gHLAUFVX3lxTE9RN1V6YS11TWVHRWZybmllVDlJT2FIaXBoVUZsSkV2d0dLd3dqVm9FR09YX3RZbFBkdDhEVDhyTm03VVdLOG52YW5TNnBjMDcxWDdBTjV2R3BwRlIwb0t1VkR4RlBGd1l3clhNRlRsMFlqeGtBSVB6ZU9zaEJyd0VLREQydkVoVzlVcHBveEJ0T1BsOVlfUV9hbWttQnlHbEdNVU9BcG5HQ052eWV4WnNGcG82LTdmOWV6V2FGRVJGTzllckd2a3hSS1JV?oc=5",
     "src": "The Indian Express",
     "at": "24 Jul, 09:35"
    },
    {
     "title": "Sensex tumbles over 400 pts, Nifty below 23,900 with Brent crossing USD 100/barrel mark; all sectors in red",
     "url": "https://news.google.com/rss/articles/CBMizAFBVV95cUxNaDNfSUtNX1pJb0NjMWtBcWxvT0RkWE1uUk9tdzFiWEo2TlVVZmtubkhsQXFEYW9HNG92amRldF9wZmlQOVRYVXpVbmVoMHpVNXpuazRJVHpxR0pxbkxBRV9XSktPQ3VtS2MtMEFnTm1jc1RRaTRTbjVnRGlJcFl5aTZ6RWVYdGdPbk42UW1feVMyTXlfNWFXVUNGSGtHZHhQMmNxbHdsaWFMZjRkMHFqMlY5SklDT3ZvVnluSmRydFpRcjE5TWJkTEJvNXA?oc=5",
     "src": "ChiniMandi",
     "at": "24 Jul, 10:03"
    }
   ]
  },
  {
   "tag": "Sports",
   "items": [
    {
     "title": "Sooryavanshi, Mayank help India end T20I losing streak",
     "url": "https://news.google.com/rss/articles/CBMirwFBVV95cUxPNFdOOE1oVkNqSUNuMFhPWkdvelotdFMzOTFLa2Z5aUlhdVdUbEF2MU9uTUxUaXM0djBESV9VMXZ1OVVGU0lMMXotVEVRVG8xUW5YR2JObkk0YXozZUJGa3JfQUljX3IzMEh5cXB3Rko2MTMtM0tHSEpNanZvNmlnYmJoU2pzS0hsaXlya09jYV9vMHFBdUFCZ2JQVmNnMVVROFBQbWNvbzZxTFN3S1RR?oc=5",
     "src": "Cricinfo",
     "at": "24 Jul, 10:00"
    },
    {
     "title": "Returning to play for India kept me motivated: Mayank Yadav",
     "url": "https://news.google.com/rss/articles/CBMipgFBVV95cUxQN21obzZLV053c3pVb2ZTZGxheF80c25WeEtFWTBMRzYyLWZ1ZHI0cjRBa1dXYmRKcjFfVGxlYjdLeGU2VFBvRHV5QXVFTVA2S0pncnIzMWwzcmdSeU1ITjM4NTJmVkNjOXRRRVVWSjA3RUVUdG5abEhzdUtmbTJjTnlHOWxwUHcyTktIbkpqN0FaSHhkTmpBd05MRS1nSnNOS1drUmxB?oc=5",
     "src": "Cricbuzz",
     "at": "24 Jul, 08:51"
    },
    {
     "title": "CWG 2026 India schedule today, July 23: Putul Sonowal to face world bowls champ; opening ceremony on agenda",
     "url": "https://news.google.com/rss/articles/CBMimgFBVV95cUxNM1FEOTkyVmRzbllmMkxOenNhRFFrWHZrdHlISXg5ZmttMklnS0lYWG5rdWRYOUdDNkFKdXExRkJMa3pmNHBhby1vSzFHSEU5U2M3b3U5d2V2Zzc3UXByM0NfQ2ZGTnJwWVBjeUFWQzhjOXUzcWlsZzYwc2RSLVBLQk5YLW1sZ2tpaWNxdHBJREVkSnI1c3FDRU5B?oc=5",
     "src": "olympics.com",
     "at": "23 Jul, 00:56"
    },
    {
     "title": "Commonwealth Games 2026: Lovlina assures India its first medal",
     "url": "https://news.google.com/rss/articles/CBMisgFBVV95cUxQTy1qOVZWc2ExaW5GeEdKQkxTTmM3VGRRODlmZ2dKQzZRVC1MMU53eUZoV2xzQ3RQSnlhUFBsaE51LUs2cTNQeXpWUkp4NjVMejk3VU1qZ1Z0TmZtSDNJdjdJUl9sWnFwQTRTWHVNVHdaYXU2ZEtobFZTVUNqNjVJTzNEZXRYdDl3ZTFFMXhFX3Y2aXFwR2pQbFFvcHVPLXBncjhyRnUzamFJVXZjOHp1anV30gG4AUFVX3lxTFBpYzFuQ0tnR01XckZKMS1faDFwQ1Fkd1BvNTRjMWZNMHVfeUZsbnpXWG8xaklDeGt5clNwMUZpXzI4WGJJUWtFRFg5ZkM3ZkliMFJIMVBTOHdLdThRcUZMNXN2WVJpelIxM3VfTmlLS0JSRWtxdGlLQ2Z2MG9aY2FoZ29hcHdSN0E3N2pTSS1sZDd1QlR6YmZGZGNaTjRVd0p0VnpWRVh1Ry12YnBOZ0Y3UWVEcmNJdlA?oc=5",
     "src": "The Hindu",
     "at": "23 Jul, 14:31"
    },
    {
     "title": "Livingstone's all-round efforts in vain as Super Giants triumph at Lord's",
     "url": "https://news.google.com/rss/articles/CBMi6gFBVV95cUxPMENPVGhPUjM0OUV3VGh2azJnMGVySUNacWx1dTFaNWl1OGxkdkM4YldBR183V250SXNWOU45SE93QzdNMUhsNVRCcGtuWnN5MUxsV1dJSUhPWWgyS3JLQVpEX2kzRmhhMm5HWEs5bEdzaXRmTzlFNnBpemNKOXZuQjNKWWNTZEFYdHJDZUFrQ2lmT2dqdzFwWUY2T2dIcEpWLXpTMU1ocC1tSzFaVVVBTTROZXNqYVBnZXJrQktIb1Y2dzhSTEhUcWZOcUJqckxYT0Q0dkQ4Rm40ZHY0azlnZy1lazRkTjFqeWc?oc=5",
     "src": "Cricinfo",
     "at": "24 Jul, 10:00"
    },
    {
     "title": "CWG 2026: Putul Sonowal stuns world champion Ryan Bester in lawn bowls thriller",
     "url": "https://news.google.com/rss/articles/CBMigAJBVV95cUxNdjlQWEIyZ0FKcEMxOFMtLTREd1RKRHNqSjE0NGhDQzlIOUtnZy1NSmNEX2xuZE01LXktblY5ZzN1eVRXY3Y2UVcxMVZhNzk4cjJGN09lNEZURURMOVVsWGlBSnM4U0hha1RVeVNzdy1BQXdCdVJLVVFLaFMzWGNQclMtRzBZcXM0ZTVzRE41cUIzY2VGMElIWkhha2JBMWVKY1RtYzZIQUZxQXF1U1FuRFlPTk9NMXJ4MlhrS2tkSndhcWFiOExURnBvUHlabm10ai1wa2ladXl4bnk1MDdtRkpzX0FYUmNqaGwtMWVrYlE2alZBOGhvd2VxT0ltU1pV?oc=5",
     "src": "The Times of India",
     "at": "23 Jul, 21:05"
    }
   ]
  },
  {
   "tag": "Tech",
   "items": [
    {
     "title": "Samsung Galaxy Fold8 series and Z Flip8 coverage wrap-up - GSMArena.com news",
     "url": "https://news.google.com/rss/articles/CBMimwFBVV95cUxNVFBTTk5WOF8xRTJHX29udmROREFTM2NJTGdqX0hiN19FUFFXRWZ4VFV0RXNLZ0drUUM1aUh2cVJ0M29LZFdEaDRJeGFFaENrRmdVQ0VHcWhnWEQ4TExvWU11a29rdERrd1RubS1fWm1kdkpRUFFLcnhDMGxHbnEyWGd0R2QyMmo3Y0kzZzljUlFjZnZfdWdBTUhyWdIBlwFBVV95cUxOV2wwZHYtcjAySXg0RzVXVUttV295MDY0Ml91bFpxQkx1ektIMVJqaGxZTjVhUFYwMnh5QkFqVy1EOVh4WXVoSTdJVmlnZlduVzVFT253ak5sM05lUnh0WlFZOE1UQnF6NWVKQ0JyajNZSEJieXpTUFlrbFdZOE83WmZ5YVROQmFyckhxSGhzaml3Mm9zV3JR?oc=5",
     "src": "GSMArena.com",
     "at": "23 Jul, 21:17"
    },
    {
     "title": "Samsung is giving the Galaxy Watch Ultra2 and Galaxy Watch9 five years of updates - GSMArena.com news",
     "url": "https://news.google.com/rss/articles/CBMivgFBVV95cUxQY0lINEtpX01qWVNxcDFQSTBmaExsQkFlX2R4RDE4V3J2aVR4cjd5RjhteHhsMlE1NlNRWi1Rcy1OOE5HcHR1NXZxdDlBeWh0LWl5TFdyRlJYcjZ1VDh4YUxwTE5Ibk01WjVVaUVsUDM5RldoREx3d3dDZnVEVmlPZENiUkwzeEJqVkRfY015cWFEWU05a2lhbm1jeUR3eVZtb3BXZ3hDMURPdEUtOHdSXzNacm5aYWp0RE9IYlFB0gG6AUFVX3lxTE1OdF9pUGNseFY4Q0MxZWZTNW5tWGhHS2pESmZPN0dPYndKY2Nkem9ETVpqUmdveVNwc2J4UnQtYnp0bXF6WUlMb21ndHM0WHR6alJZMjBibXExbnE1b0dGYVVPbXhKaGM2Uk04cVFEY3dqQWFPUzA1REl0Nml0TVJFYmNCeVJnZFZCNUR1X0ZmLW9lU2tWaE11M2dBb1F2WkdlNDk3ZkxhVmFxTFBwVS1ua09jNlZnRDhJQQ?oc=5",
     "src": "GSMArena.com",
     "at": "24 Jul, 01:18"
    },
    {
     "title": "New launches, financing may give foldable phones a boost",
     "url": "https://news.google.com/rss/articles/CBMi2AFBVV95cUxORDYycEhMRU9tdHpULVo5MkRUOVQ1ZjVwbnpVaDh2MllOaWJoT2t4c2JjTGk4Z1BHX3pBZmpqTk1KZkhBUlNHTjJPX0NfSkE5cnduRlUyazNZZm5GdGl0QzgtRVFSZHIyNmlZeU5qTkZTZUFJR1ViTFpSdkpIX1lpNkFraWdJQXdwUElkWlduQ19oV1RsMU9WQ0NiQ2YwX1BVUU50Z1BLOTdKZTBRX1ZqVVVTLWRqY2dCQ1NXRzBSUWhrbHZWbUpEa2FRWnJ4bEcxZW5vSS1QaEE?oc=5",
     "src": "The Times of India",
     "at": "24 Jul, 07:28"
    },
    {
     "title": "OpenAI rolls out ChatGPT Health to all eligible US users",
     "url": "https://news.google.com/rss/articles/CBMioAFBVV95cUxPUVhOdlNyWHZzX195UzI2eE9ndkd3TnNFWkEwc0xzNVk2M1JWQVd0cTVTRVZuTDhSVC1ueTU5SXRzWWwzVnI0ZnQxWF9TOXRzOU85NVlZMzVoMUUxMHJveDU2NnV5RlJFWkQ3cEVGaGFMY3lpakR5YXhqU21SYjhDZ2FYZTAzSG5iN0tpNFRCZjY3alpTOGdxR0JNakh5N1Vi?oc=5",
     "src": "t2ONLINE",
     "at": "23 Jul, 20:39"
    },
    {
     "title": "vivo S2 India launch could take place on August 6, design and key specs leak - GSMArena.com news",
     "url": "https://news.google.com/rss/articles/CBMikwFBVV95cUxPZENEOUdpT2ZONHpWWEVENlVzVnlheVhPeDduSUczdUlEN2dBUXo3aE5pbUV5aGIxOVV6alZXa0paSmM4QldURmpRcW5FdUdYT0NGR3lmZFBGenJrX3I3OUFIWXlwYnBIUUI5bDNTaUR3ZWE3WkFvRDVkWkppVXljX2o5b2JUU3pZSkN3ZW9OeUVpU0HSAY8BQVVfeXFMTnRHT1kwU3JCcXNERk1CU0pfWld1MnBnWnM5UkYtT3YtMHF0RklOc1liVHl0clI0dnpxSkxZUThhN29McmdZOGZzNHlsSk5qWXBUUHZRWDhCQ3dPVTZQMzBrOXFFUlprN1hzS1owekJIWjIwYnpPUzd0VmFVZmF6U3hRSFpVOFYyUERoTHdONkE?oc=5",
     "src": "GSMArena.com",
     "at": "23 Jul, 17:19"
    },
    {
     "title": "Samsung brings Galaxy ecosystem into eyewear",
     "url": "https://news.google.com/rss/articles/CBMilAFBVV95cUxNYzhPUy1JNDI1MkNqa3dBeDZobWQ1VzJNb3RBYmp1czJJSVJsR01LdGxVR1prSDVwS0tPeEo2YllobUVXZnFqVEkzZzlFYm5kQmhZUko3VTRVWGdQRHJwdW54YmRHbXRaZE1YbDhuMUlFNV9XbVhXUTZJb2tGUUVPbjBBQUpuRjNPVUJSZUlxR1BkVURF?oc=5",
     "src": "Computer Weekly",
     "at": "23 Jul, 17:49"
    }
   ]
  },
  {
   "tag": "AI",
   "items": [
    {
     "title": "Artificial Intelligence and the new gateway for Chinese Influence",
     "url": "https://news.google.com/rss/articles/CBMimAFBVV95cUxQYmxuUkpKNlJ6VmM0N2c3TXhnWFF6dWZ6Z0s2SGJaQ3A3dnFkT1p0QzhHb3lPMnkxQm5fWnBjODhHcWdzWVlNNmc0aXRnSEVRLTI4YzE4aEtabHR6UWpxTFo2cjc3ZV9CaEVValJUMFF0bnV0WGJES2RKNUpsbDdYcGtHaEY2NWwwMnp1WlJoRDFMMkVjbFk4Yw?oc=5",
     "src": "Decode39",
     "at": "24 Jul, 01:24"
    },
    {
     "title": "UNESCO and LG AI Research Launch Global MOOC on the Ethics of AI",
     "url": "https://news.google.com/rss/articles/CBMikwFBVV95cUxOS256RTBsT0lHUWR3QkxoMml2U1QyUS1SVS1mQXlZd3ZaUldGSWwyMGxhdHYxYTFycC1ET19Xc1RvaTg0X2JOV1NxVUN4QXhBNHZWY3ppQ1o5cVhBZ1FPcGQ2UXljTWFjVW9zN05DdUZPUXU3X0tkMHN2NXM0a0NJWE45bVdTbXp4U3ZLenFZNTVMNzQ?oc=5",
     "src": "UNESCO",
     "at": "23 Jul, 23:03"
    },
    {
     "title": "Artificial intelligence: Moving beyond the GPU",
     "url": "https://news.google.com/rss/articles/CBMipgFBVV95cUxQQWJzWnNFY1c0d3lpNE9ObGtmYjlwWFFoUU9wVHRwTWhMR1pQZThFbXVYT25yVGl2TjRrQTRmWDNHemJ3anNUWFRHREdncGR1eE5rVnhkbnZiaUVWYmk3MGVxekNrNTNlaDJsWDBGUlhKakxRWUZZaEdVTGo0aGxJUG90NF9LckMzQ203bGJDOWlKNnFMVFNJSGxZb01zSGx1RTFzWEpn?oc=5",
     "src": "SiliconANGLE",
     "at": "24 Jul, 02:51"
    },
    {
     "title": "CSIR-NIScPR Released Technical Report on Human-Centered AI and Hosted Distinguished Lecture by Ms. Debjani Ghosh",
     "url": "https://news.google.com/rss/articles/CBMiekFVX3lxTFAwaGJ5NjFzX2RyTlZpYjNvVEJnaFVnWGgyc0NhZWpmRngwdUtldzNLRVZzRnpoMGZaZEk3NzFxQ2l4T3haOEwtZFc5anlPU0pTQXgybzItZWg3S0Y3YWNYcERCWldNemp6VUNXMmZxNXFHTzYxUGRFazR3?oc=5",
     "src": "PIB",
     "at": "23 Jul, 19:50"
    },
    {
     "title": "Lenders on top of AI will lead digital lending",
     "url": "https://news.google.com/rss/articles/CBMiygFBVV95cUxNRjgwbXh2VmhIQUxJY3M0Z0J3OVNKX2R6dHRuZ25WR0tPMTJ6NDFXVXIwM2FBMVlzVVBxZnA2ejNJQ01HazVrcnVpSXY2YS1ZdHpsMHMtS2tWSGptZ1BmVlVsSkV2TXRKOGlkZEE4eXBteGFqRTMtMG44bEM5Q2RBZVIwNVhfSDdQQWhSd2ljalJQcE84VnlvOFlRRnNHQXdFLUxBNXhDUjhMVE9pNkttV2V6TUtVRXRZUU03SFc1cGZHb3dId256b1hn0gHKAUFVX3lxTE1GODBteHZWaEhBTEljczRnQnc5U0pfZHp0dG5nblZHS08xMno0MVdVcjAzYUExWXNVUHFmcDZ6M0lDTUdrNWtydWlJdjZhLVl0emwwcy1La1ZIam1nUGZWVWxKRXZNdEo4aWRkQTh5cG14YWpFMy0wbjhsQzlDZEFlUjA1WF9IN1BBaFJ3aWNqUlBwTzhWeW84WVFGc0dBd0UtTEE1eENSOExUT2k2S21XZXpNS1VFdFlRTTdIVzVwZkdvd0h3bnpvWGc?oc=5",
     "src": "ET CIO",
     "at": "24 Jul, 08:00"
    },
    {
     "title": "AI may replace jobs but create new ones: CM Satheesan",
     "url": "https://news.google.com/rss/articles/CBMisAFBVV95cUxNQUdrWUxmd182V2QtajVhbUlUUUtKVVJaRVZPZDMxZGI1NGZmR25JSjRHemdOTWxTaUZXdDRCTHFQUXFkRGlDVW85eS1YSm9rN1FtZEJuV0JtOGQyc1Z0U2Z1YXloOUJoWURrcUU5OTdMVVlSZTZNb1ZTYnpMMlFsWDZtOXBqa1RvZXg2T0Q3cWw0c3V5Vm51VXJUWHlJWmttMGlmcktib0lQdFlfSUprZw?oc=5",
     "src": "The New Indian Express",
     "at": "24 Jul, 07:37"
    }
   ]
  },
  {
   "tag": "Economy",
   "items": [
    {
     "title": "RBI keeps repo rate unchanged; Projects India’s real GDP growth for current fiscal at 6.9%",
     "url": "https://news.google.com/rss/articles/CBMivgFBVV95cUxOTGFSNzg0VzlJdnMwYWh2TzliX3libXhnd0pFajdsbW05R3dZU3Y5V3BjRU5uV2Q0aDVOZWZNX3dDdHpvNXpGOXRTQlNnQVRScklzNU5QdjVmV2YzOWlFVWZXMXFSZWxscFJIdFY0UHhleHZreWhkRmhqNGpCeTBYTVlpZ3AxcFN5X0h6SkFqSHJzSTBhWER6N1lkQXB3cnlLRXU4TF95ZjNWdC01XzBkTm0zOGN3RmpXc1lQSkdR?oc=5",
     "src": "News On AIR",
     "at": "23 Jul, 23:59"
    },
    {
     "title": "Global growth to be marginally higher in 2026 supported by tech-related investments: RBI Governor",
     "url": "https://news.google.com/rss/articles/CBMivwFBVV95cUxQaFJ2QVFNZUJVa1Rvb0NlWmhiYmNhNWNRMlVlYUNHSGY0c3UwcWlrYlVpRmR2RFI5dmdEUmprQ1NkUGlYUUpkdUtISTFYLWJPVVdXT1Y4bUt0ck5HN3NueF9QQUxobWhPMG92ZnpfdGVPUVNvYUpPXy04b05OS3B1X3preFlkbVMzWnY3LU4yU3VicmpKOUw2UV93UEZNZ05oOUlGaHQ4UUd2Y2c1cW1PTHlkVlF5WGE0WS13TmJNbw?oc=5",
     "src": "DD News",
     "at": "24 Jul, 01:45"
    },
    {
     "title": "Indian Economy Sustains Growth Momentum Despite Global Uncertainty: RBI Bulletin",
     "url": "https://news.google.com/rss/articles/CBMixgFBVV95cUxPVm1IeHh0dkk4M254Sk1wUG1oMFVPdHF2b29TcFJZOGNiMG9KNDZqVWJSdW1QaFBNZFZ3c1NXdU4xVDVJV1gySmZlakxNYlZYYlBuODVLWGdNWmtsbTR6aVh6Rld3cGpCVk01U2FGc1loRVFFLVZMdFBsYUl3WlFMbko0THR2Y1MxRjliV0toS0JuQ1RxX3hoOUdsWGY2T1AyZHBGWEZYOFlGaGlMMTdKa2FDeG45SmVKTXJVMERBb0lTaUU1eHc?oc=5",
     "src": "KNN India",
     "at": "23 Jul, 12:45"
    },
    {
     "title": "India navigates external uncertainties well in Q1 FY27: RBI Bulletin",
     "url": "https://news.google.com/rss/articles/CBMi3AFBVV95cUxNS0FxTU9FQU5sbm1Nc3RFN0k4UXhaQUI3UmdnQWpuaGhQYkpTM3hCWFduUjlNWENXeUlrMEZFTThqNFJISWtwSjVidjBjYmlhdHlEaTFvMURCMVAtVlJieHlKNVRLWWwzUzMxcFNCUVFyem80ZURnd3p5VlZOSktjV2NFX2tTNnZKTklFdVRGS2x1QTdBdHRCaUhYbzBDVWZhQjJKbjYxYUYtSE93UU9xMGJOWXAxSEdSYWFRUGEwRGpLX3E3dko5TDI3MFQ4VWJqdmtUM2ZRUnFqRFB5?oc=5",
     "src": "Fibre2Fashion",
     "at": "23 Jul, 16:58"
    },
    {
     "title": "Indian economy navigates global uncertainties effectively with recovery in foreign investments: RBI Bulletin",
     "url": "https://news.google.com/rss/articles/CBMi7AFBVV95cUxQdGItZmxGeEdUMHJZQllFMnZhTThTazNRZlZWa3luV1NNM0JLcHA5TXN6aDdPOWFmT0x1dVAwQXZaamM3Y1BrdTNRZ2FFZGxwY3BiekZyZkRMc1hQQ2k2dks1RnptWW1neGJ2RXlWbHZjRG4wQWpaVmo0cFl1eDJYOFRwbXJWWllmaUhpNlNLdmlSYlhnd2N0T2dfVTVXZXlQYXpVNzZkemw3dVhYSXBJMmJETXo3TlVZbEFmVDZ4UWtEWWt4TjdlNzAwSXNiTWhka1pzS0FRUHI1VFpobU1sU1VNc3FTRkFVNGo3cw?oc=5",
     "src": "Investment Guru India",
     "at": "23 Jul, 13:16"
    },
    {
     "title": "Indian Rupee Edges Higher on Likely RBI Intervention, Traders Say",
     "url": "https://news.google.com/rss/articles/CBMifkFVX3lxTE5wWlgxcS03LU56V2doWHZ4WGxDVTg5MmFUZTh3cUdydm4wZGw1THloVzRDTzN5bnh5VktSemtyQ3ZnNEpWNEVlYmViY1R0Q1BNSjNoSkdUY0tEQjVJRTQwMWhhVFkyVEh2N3FvLUxWZ1JpU1ljT2E4T1JzRGduUQ?oc=5",
     "src": "CryptoRank",
     "at": "23 Jul, 16:50"
    }
   ]
  },
  {
   "tag": "Politics",
   "items": [
    {
     "title": "E20 Clean Fuel, No Plan To Return To 'Pure' Petrol: Centre In Parliament",
     "url": "https://news.google.com/rss/articles/CBMirgFBVV95cUxNUkdDZnFKYWJKYVlMNFU2aG1qR0Vrc2ROSUNwQTNIM2pMaTNKb1VSbnc2bDdQSkpPeUdsQTFWWXdVTmFsUTRqbEJ5MGxXc0pCWXdlR1JBb1dNeG1rQ0VaSXFKQi0zaGo5V3dGc290QUZqODRNZWdURWl4N1U3RjF3bmdDMURzdlZVd3Z2X3BhMWtROTIyY0dSX21ESjVtR0gxbDlDLVc3c0xKOVB4TEHSAbYBQVVfeXFMTUlKalJpMmZyODRHVFF5NE54RW5HODlWdjZKS0JZTENYTWc1YlFZczEydU9DYkhadk5ucThPQTdEUXdoUnlkWHpuaHNQUGhUcHRhUnRaRlRhM0t3NHd3QUM2QWo1dmZvdjZ6MEIwMGVFR2pEZG9BZThfeWVwV3FjSG9hUFBIVjNRVE5BNUJVYnNmRU1BTFZZaGRyNVNTaU9HMlVWWDVCcEx4dTVGeE1WeU8wYTNHY3c?oc=5",
     "src": "NDTV",
     "at": "23 Jul, 16:46"
    },
    {
     "title": "PM Modi emphasises women should be made part of decision-making process",
     "url": "https://news.google.com/rss/articles/CBMinwFBVV95cUxQOVpocUNJUThRbllFWmdOQVQtaU9ndUNvYldJNHZhcDhKR3hiYmN3N0xNSjd0YVQ0U0Uya3JwNjNTRWtKYWhKbllIRzRsWHk5a0wtM3ppTThEMlppU3cyZGFUSUNHdVFzdWNVc3ZKcmlJa284WldVUUdIbkN3TmJveXctOHJlakJaMWU4bXUyWURJV0p4R3VQb0NCNXd1UmM?oc=5",
     "src": "News On AIR",
     "at": "23 Jul, 15:37"
    },
    {
     "title": "CJP protests at Jantar Mantar: The youth movement India's Modi didn't see coming",
     "url": "https://news.google.com/rss/articles/CBMiWkFVX3lxTFBiLWpWRFRvUW44Y2hFYWhBQXgtWmI2RTV1RFkyT0NfMXFJVGlDQ0ZHTGM5WGtUaFZZaWQ1ZFBTSk5hRDFDX19ZeEZRc1RMcXpjZElmZGJ4VW9Ldw?oc=5",
     "src": "BBC",
     "at": "24 Jul, 05:11"
    },
    {
     "title": "Sonia Gandhi writes: 'An education system’s collapse, young India’s trauma'",
     "url": "https://news.google.com/rss/articles/CBMixgFBVV95cUxPUkhuSnFrSS1tbkRQdWVEcWRFSmRDeFhCM09nOGJ0VDBNSE1iZXJxbXJqWDlFeWl6WEJNZDg0YVFDV0xlMWlDVTJySDZRY280TDhrOTRrbm96U3plTWJJZkk2aFBGeHVBQ2FVd0FYS1JsWWI0UTItdkZ5eWtiSEJZbEk1Q1REdnVFUGwwVXJWQmZYQlNpUU4tcGtvSDlCWjQwUno4MS1UOHR5bTRZcF82cTluV3BNczhYX0hkMWNKdUdyeUhXZ2fSAcwBQVVfeXFMT3Y5aVk5bmZlR1U0VGc4RlpOYlFEWDIwUjNTMFllOS1PRzNNYVIxc0pMWG1JTmtOODBZV2hOeXR1RV93b1J6dXd1TU1GeW1vbDhZR1duNXNOcENzdHRmRTJCMUJlVDktMm00UXpyUmtJR0JuMnAyZUttX2MyZWFJQ1NleWQ4UVRBQ05DaUROdk1PaUVUSW1TYkx6andFTENPbWZQNWEtSmtTSGJ1M3RWYjFJWmtVeXIzcVhXNGVzN3o5SE93Y2QwcG1Bb1FX?oc=5",
     "src": "The Hindu",
     "at": "24 Jul, 00:16"
    },
    {
     "title": "Govt informs Parliament no private nuclear licences granted as SHANTI Act rules in drafting stage",
     "url": "https://news.google.com/rss/articles/CBMi4gFBVV95cUxQbEFEN1U4M25QX3F3WFZtazhWM3FNTzBORk9meWF5WkdNdGF6a21WTGZLY0xKZEI4OEQwTzJVVmd2WXBnZjFIUnJMX1RrWE5WVG85ZjBfUlZFaWYzanJJbEJOM3RVOFh3RXVkOXhjZXZ2X1Y5YW10TlYtRktsbGdjV052SjVOYlFjNHNTNmdHdFNPN0poRHc4SkNKZHVxcnl5QlJrR1dBenJCODhxRTlaZ05ucmI1Y3RyU2lpY1dETGdXa2ZtMU5CWDBwOEIyUnJ1cUJ3b05Tc2o3Zjh4dVVkQ2xR?oc=5",
     "src": "ANI News",
     "at": "23 Jul, 17:13"
    },
    {
     "title": "Parliament standoff: Government reaches out to opposition for NEET debate, urges talks without preconditi",
     "url": "https://news.google.com/rss/articles/CBMihAJBVV95cUxNTjAybzZoRVhWR1dOcWt6d2tBSm03dURVdjVRQzNIVUt4SHlrdkx2bVAwYzJjc096Sk9ZWC0xUS15UmRkckdQLV9NamI0Wkktd1llbmFOQk5Rdy1sZmlZTWtBX0JwOGlyRE9EMGlVckxWWlhGRFUycDRMVDk1U0M2OGhNVjl6SHRjWmVsb19zdXR6ck5SYXRrR2VJTGN2cTBXVldVdldGR3luMVczWS1JbUd4clJBeVRFYVEyNlpvSTQ0UkJwUWZlSWhZcHkwMk1KS0IxQ2pxZmV0bjhObngyRUw3ZVVkeklMcDVJSzRwVUlwSTNOWHNCZTZuSzBKZTVHQ1p2ONIBigJBVV95cUxPT1VQMlJ4Mmx0WWxoc295MllCWnFiWlhtWktLM0NJS2NQTVN4NzZGcGg4WE9CZ2lIaUpZMGFkd3ZXczVsbGY1eUZ5SGV3NjYxMmJFY2dvYTZUMWlmSWZRRlRIejZnWFNkQV9Lc1NKR2Z0R1ZTNlNiRW0wWWVsYmRVR3dFcVUxZ3Znanp5WjZuM2MxbUV3VFNzSTFia29Fd2V5NUE4XzBwNG9JYksyUlgzYm9lOHhWVGVlZ0s1NnkwSmRvQkx2Q0RHNUI1a0xDTmZrYjhURjZNeDhXU1ZDeHZER2NsTEltS19VWVV4QUg5V2hCcDB3ZUZfRzU2OTBpbUwzZmlrU3lrZjlhUQ?oc=5",
     "src": "The Times of India",
     "at": "23 Jul, 16:00"
    }
   ]
  },
  {
   "tag": "Jobs",
   "items": [
    {
     "title": "Oracle Layoffs 2026: Tech Giant Cuts 21,000 Jobs Worldwide as AI Reshapes Workforce; Indian Employees in Focus",
     "url": "https://news.google.com/rss/articles/CBMi3AFBVV95cUxOX0txa3l0Uk16TzQ0NVcxbVBod3ZfSk5FQU9HaG9FNWd2VTd3VGxaNHJsTmVlVHh6VnhWQWdOeFZmSER6dFhVY3RDUGVZQkhuR2pTelVUMXFqbUpBYWZSMlFpU0lzcFRUNzJWQWtTMjRFbFlMZmpjTnlDLTRwcEd5aUo0VTh4OXZlTG1uZC1wR01La1c3R09tRDQ1MGEzTlpYV3ZwVmRuZG1XVWZIVVpkdjFRdGpWR1IxSjN6U1ExQ09tQl9uYmRvWjRwbEs2Uk9CVUlSNVFXWk4yUmU3?oc=5",
     "src": "Goodreturns",
     "at": "24 Jul, 07:32"
    },
    {
     "title": "Amazon and Meta laid off 40,000 employees in last 10 months",
     "url": "https://news.google.com/rss/articles/CBMisAFBVV95cUxNRk1DSHdzNF9nY2JBTG0zNkFpWTdVQkppU2t3YWdfcUtTU2NncXNQTHhIYTk5Q2V0ZGZuYnlleDczY3VLRDNZd2dna3hydFdNbXRRcU9MVVR2OG5SRjZxRFAyUlhKdThONFhmb0dXbzdUbDlrLVJNQnVhSFI5UjZrNDBTR1VOLWxMVkVETE80VlpwSWw3Wk9UZThVYzJBLU1rUnl4c09ENHVVZHJYZm9pN9IBtgFBVV95cUxPczNlbHVWb1lqZExfY1JSaEZ6NHBYWlpkSV9SYlM5M1FvU0ZXaVA2RU9ha19xME5lbjAzejdQUjJJeXN1WVhaZU52aXd3cTdfR2VoYnRyeFR6RnFGeEpJTEI5ZEhFUm81TUxkb2R6ejNCVnBoQjNFSGVaWmpSWUlRU2hpSENHZzFaNGdPbGNnWW1IUDk4TEx5bHFwSlpZUlRjN1MzckhLWUlQWW9xMnFZUzhGOW9Wdw?oc=5",
     "src": "India Today",
     "at": "23 Jul, 16:12"
    },
    {
     "title": "Amazon cuts jobs in AGI unit as it sharpens focus on key AI projects",
     "url": "https://news.google.com/rss/articles/CBMi0gFBVV95cUxNWE1zZFlwUnBrekpid2NsMl8zd1lIWW5wbC1NRGtvdWlWWm9lQUdqckw0SUtoaUcwaDZvRzh5Q1cweDdyT0V4dmZhSzNHeG5CYlFYcEg4Z1ljQXJWYmgtNUtnWnlWQVJ5bTdpd0JxWUs4Qk1FeFRFb2JyZlFua2pjODg4YnowLVpRQkg3X2FTUlhzM2JuMW5YaFl4ZUVHS2Qxc19yMzJ0T0RvcTBTdGIxclFsWjg0RDhGdm5NOVZPZU1NdDI2Nlh5UFFMNVFnN01OVVE?oc=5",
     "src": "Business Standard",
     "at": "24 Jul, 09:54"
    },
    {
     "title": "Uber lays off 10% of customer support employees, orders remote staff back to offices, and the reason it g",
     "url": "https://news.google.com/rss/articles/CBMiuwJBVV95cUxNXzB4ajR4eU80RDVLWURPaEJFMy1FYkt1aVlMSHN5U29BLVpRQ3EyVVRJX2FIbkZwa3ZFVWlFU2doUExCWV9ydUdyTjVRRlU4YVE2VVhXTk5PTlVOSW52aFdvd3BCU3M5UmxjRUFhU2NMQklMaU14TEFVMXpIcWlacDBXNnBWelNDZHB0dnl5VWlwZGx1WnRQMTJTN2xJLW9kQWd4SDJqNC1ySjNlQ3NUYzFSaHNuQXVsbmtQN2FsN2FDaFlCclQxWG1qSDJjWGxIWXA0WjlvZWJzenlHLXNiNG5LMk1NYUYzZmZ6azRlMlhIU3lFVkxOTmxpbTh6UmxUaTFxaTItZTh2dkhaT1l1NTJ4eVVEOHVjbEhBell5RUFVMmltVXhaUWQyZ0xyb1NXQ3d4aXh0UDQwVTTSAcACQVVfeXFMT1dzWHFpYjdfV2RrQk85M3RtSFNQUHFuanlzS0F4WFRyMEJRY0VPdzc1cVRDSWFTcWFLMm5MZFRUSnMzbTFhbXp5bHJmUUhIU3k1eUYtUDR2SUdjNWhVNWRZeW5ackxMdllfeGdlbXBEVDdoSDJiQ1NhRVZiakNfXzI0azJscXhNekFxcC1IVFVsblMtRUhEQnhmUFMzVUx2R0FNTjBYYXZaOGQyTTBIR1UxNjU5RXI5a2NxY1MybTRiRmxEM1N3aEdnbVlUQUNydWxkMWJKZDdzalF0bjV6dG9hSHBTTzVCSnhkdFZ6VTZtVHR4cWdueGlWUzVHcUZaeHFDZlJ6aUlhMnN6Y2dMVlBVZGNhQVlHNU5KV1p1S0oyU21ZaWFZVHlmSXA0NjRIMXB3SEVJVC1sM0hHOTUyRzU?oc=5",
     "src": "The Times of India",
     "at": "23 Jul, 15:11"
    },
    {
     "title": "17 companies, including Uber and GitLab, that have said they're doing AI-related layoffs",
     "url": "https://news.google.com/rss/articles/CBMirgFBVV95cUxOc2ROSlNIeUl1cFRzVTJGUzk3TjFkU2RDQktwdXQxemhxNDFPRVcxd1Z1S21uY00wN1RvSWdSOFYxZHhSX3FObU13bFMwSXZEWnVMTHFMUzNObnlRNTF5WWRDcWFUOG9XSjNiQjUzMkxDc2R0ZDJNQUI0dzZTcDRvSlY2TnljdE5rTU45LWRkaEwyU1VDbzFaWk42N093Ri1MMl9CRG5feVBRcDBhbHc?oc=5",
     "src": "Business Insider",
     "at": "24 Jul, 09:10"
    },
    {
     "title": "Fierce Healthcare Layoff Tracker—Novant Health cuts 31 rev cycle roles; Dignity Health lays off 139",
     "url": "https://news.google.com/rss/articles/CBMiwwFBVV95cUxPUGotbUVRVDF3QVpWdUJURDNNbjNKMDVaeFk1aUJYRVZTaE9jNURGRmlubTRUWV9aZ2lMdUxoa3d5QmtKQk9uRlBzMV8zWGVuSDdmNU5xc1F5ZWFvenF0bTc1SXBxWkRMWHcxREVKTEpoQzAyYlVQT0NKX192bmdBYWlRdllFOWJGOVJ6UGJla0pqVVJHdE9vdDlmZEFBa2hxaXJwa1M2QWJwN0lTbVp5LXlXZWN2VmNSUmRLWjdvRy14ME0?oc=5",
     "src": "Fierce Healthcare",
     "at": "24 Jul, 03:22"
    }
   ]
  },
  {
   "tag": "Crime",
   "items": [
    {
     "title": "India signs Mutual Legal Assistance Agreement on Criminal Matters with Nepal",
     "url": "https://news.google.com/rss/articles/CBMipAFBVV95cUxPcGtCeDhiUEtLTnVJd3BPZnVOdno4aHhXSGNiOFpaYndTQzNwQ0tTeDYwYWhfUWJNNDVMVnRHUjJ1eXY3MnJ6WVRESWsyUFFhYkdJc0hpc19STC1manRtWkVKSElKaWIzRkN3Y3ZDYXQ4SWt5c0daOF9xQm8zY29RZWdLQ3AxSy0tTFJNRnliRnNfdHBOU3Rhb1otVVZLSDBONjJ0Mg?oc=5",
     "src": "News On AIR",
     "at": "24 Jul, 04:02"
    },
    {
     "title": "2 men stabbed in New York City, Mamdani opens hate crime probe",
     "url": "https://news.google.com/rss/articles/CBMiqwFBVV95cUxQd0Y0M3VxczhXOWxvZ25fSVRNeUJERTJfbmZYZEV6dEJmbE1OYTBCYTFtcUwyVHBuUHhJa3RsdG5JSGZtSTRPTExvNU82VWFOVjFaMm5tWHJHaXVCeGlnakY4b2hWYWFrVkdLUnhXVVk3a3hiMVgtbU1Kbi1IbDY5dHp3N1NkMU9VRWVDblAyMkJXNHZ0QnYxbHJhamJteWtCVVpHeHEzRWVTdTjSAbABQVVfeXFMUFk2dDF0T1NHazZwMm9Dbkw4QTJqNEZvaWpOZFU1YmVBOW8tbHVWVmRVTk9fc0NuVkstQlMzVDVONXA2UlgtWjlwQ2lPTHp0a0t2blFobDlPTFFVdXFOQlk4WV9uTUdGcHZkckczVk5Lc05EM1FhUG0wdnduaWR4MjhRUWlkeWhuVTBCX0NSTms0U3pNQjlycWo5Q2YxS25RcEtQaW9zU0RhbEVFYTgyM3I?oc=5",
     "src": "Firstpost",
     "at": "24 Jul, 09:14"
    },
    {
     "title": "Special Report: Bengaluru Triple Murder | AI Chat Allegedly Helped Plan Family Killings",
     "url": "https://news.google.com/rss/articles/CBMizwFBVV95cUxOaXVON2NuelprS3JxMXV1elNhZUM0akE5M2I0am4yS0ZaUmhJcE11Qmt3d1NwdGNmQ0dxTGFEcmF5cVROZm45bE03V2VoUmozNjVHdEVWSE5kN1ptWEgxVHhwX2Fwek9LelUyTVhVWnpOeGRiTm9CUHN2STlyWUJoSDVkR2RWaU5URnkxNWdYRURwOFBFbV9FcGFLQkprSjVfc0c3N2Q4b1A0VHpfZlNYOWhSSUhLaDJKMC1kR0F5ZVNNaXphTWROWTNIdjFyeknSAc8BQVVfeXFMTml1Tjdjbnpaa0tycTF1dXpTYWVDNGpBOTNiNGpuMktGWlJoSXBNdUJrd3dTcHRjZkNHcUxhRHJheXFUTmZuOWxNN1dlaFJqMzY1R3RFVkhOZDdabVhIMVR4cF9hcHpPS3pVMk1YVVp6TnhkYk5vQlBzdkk5cllCaEg1ZEdkVmlOVEZ5MTVnWEVEcDhQRW1fRXBhS0JKa0o1X3NHNzdkOG9QNFR6X2ZTWDloUklIS2gySjAtZEdBeWVTTWl6YU1kTlkzSHYxcnpJ?oc=5",
     "src": "Kanak News Odisha",
     "at": "24 Jul, 07:15"
    },
    {
     "title": "National Cyber Crime Reporting Portal Saves ₹11,158 Crore",
     "url": "https://news.google.com/rss/articles/CBMiiwFBVV95cUxQZlVOZEJXdEFjZC11djBwTDVTc3NPeEd1dm56TTlEbmZIUDVOTElOS09oRHFQOXNKNndTNGtDOGM5Y0dwR1dEVmtnNjNOT3V1alRJRFRuWnJ5enphbFJaVVZoU0p1SGkzLXRkODRnNWktLVUxS1JFT2lvOU5KLTB2X3dLeUxPcHVTNURn?oc=5",
     "src": "Sarkaritel.com",
     "at": "24 Jul, 00:17"
    },
    {
     "title": "Complaint seeks FIR against Mamata Banerjee in anti-rape activist Barun Biswas murder case",
     "url": "https://news.google.com/rss/articles/CBMi6gFBVV95cUxQclk0MWZCVFp4cXExQ3paUUJlWUczSnlROXNUWVRiMUUzNWdqWWhHTXdKSkVoZWpLWHdobUZLbHdwaW9TR1pXbDU2SjZZZk9QOWZyYjF3Yy1IalFCalpqZ0VWZ0NGLTVkc1ZSYXZEZkphajRpMFlhTVhsd1MxMWtzVTFPM1hDcXpVRUJzc2lySU1sd3YtaUUtYl9fODlDSkJvcER3WmRCOUp3YnZCNEdhRThsOXRpbnJZNDVQZk96MndiNm5FYXNjUV9zV1J2c3NWWVVxc1lxYng3WWEyOTk0TkFmZjdaS3czUlHSAfcBQVVfeXFMT1Fnc3R2UU0xZDB0WjRoZDc4Q2lYZHJjbzFkc2p5dElvRmRmMkVDNTJVYlFqYnlMVUVVZWlwZE45MnZNa29NaXZuRWlLaWZ0VHYwbzAwZDl3WGRpTnQ5eTZUYll6VWZ6UlFiZzE3a05KU0RpVFdXWHNoUEQta01Qd3VmNW1CMml4U3NuYXg1TkNkUmdMeGt2M2VIU01HdlFuMmtBLWpjR01jWnk1OXN2aVMtQzFzMF9ld0lndWNIYTR0Tlhvb25EX1NCX3VZMXFscXdDTDNBUUhMeHh0MlFRbzd6QkZvdTdqejg4RUd6VVFkMW9qdm5Fdw?oc=5",
     "src": "The New Indian Express",
     "at": "23 Jul, 20:30"
    },
    {
     "title": "India dispatch: Delhi’s “Cockroach” Janta Party protests police response",
     "url": "https://news.google.com/rss/articles/CBMiqAFBVV95cUxPeEdreDJ5ZW5qeFVFSWVLSmt1WTNrYWJuSFBLY0NSM19HSFAxUmJPc3FaTGpuMnhtU3lPa3VYQWl6bFFBMGxEd3VJcjFWSUxpcDFIMzNpVE1UT2V5MXNBY1dSU3dMRmZYbm9DYXUxZmhrbnZLbEFTZGdOaGZwdlZvSk5XdjdlY3kwbFRjSzl6NWhBNWpWeHU3emtxVXNUUE93Q0pVODlNTnU?oc=5",
     "src": "Jurist.org",
     "at": "24 Jul, 02:07"
    }
   ]
  },
  {
   "tag": "World",
   "items": [
    {
     "title": "US Strikes Iran As Tensions Escalate Over Shipping Routes In Hormuz",
     "url": "https://news.google.com/rss/articles/CBMiugFBVV95cUxPUXBOWnNuc3RUUEZKVGNUaFc5bGlpOGR2NXk3TTYxUTk5Yk12T1c5cDFuYjRQbm1JRGZrSTZHVTNVSXYzdFlCWExvd0xvSzRCQ0JXMXF2c2JGMFFFMTE5YWxidVpaM3NMZVBUNS1SRm1YSDAzLVEzZE9ucTlISWNQQW1iQlpuSy05MzR1ckJjeGVjckoyV3hmNmR4cS1SVzlXV1ItazRBN3FXVlZGTmRSV2FLdU9oaFd4NGfSAcIBQVVfeXFMUFBLWmZQYmd0eUdPMThwSHB5RzNoWDlaSm4tSjZLaFNZN2U1TFptb0ZkTTU4NXBxaDdPZjl4RjdycDdMSGVSSUxPTUFkdXdhRG56ZkhKNVl0MEhOSjhXcXFxMFh3QmJkYWtKYk5pZm5lbFBXLXJmSC10ZmU4N2M0MFlSN2hXVDUyU2hEUVZvTDFzS0tfeHJyaDdQLVhuYWRQdTBjaUJRT1B1dHZOd2c1VWd0RmRSWmJzU3FNb3FWTHBHamc?oc=5",
     "src": "NDTV",
     "at": "24 Jul, 04:59"
    },
    {
     "title": "Canada PM Carney: Interactions with the US this week show a level and a breadth of engagement that reflects the seriousness of relationship",
     "url": "https://news.google.com/rss/articles/CBMikgFBVV95cUxNQUlnQ01fZmpFV1JhbVB3MkpvWkxfSGE2NTF2NHBPQ1RiNTlTRFVXWWJVZmNZX3NQVEgwd1gwMTJTcUo5WjJfU0lMbnpMSmNlVXRkdWk3M2VNdEhoSGVFdWdJMmNPXy1SaDNFUnNfcHpTWGdtUFBkaWhNbUJaU2lsQkg0UUl5d1dJQkR5Q1J2c0ZUd9IBlwFBVV95cUxOUU5sc0ltbnhRYmRNYzQzUzRpa05nV0NpWWk0SmtHZTBuMlJSeXh4YzNxZndvS1BXa2R2SUVuc1pQVlVXRU1YXzZRSUZTblVBVnFCTThXb0tMOW9oWDIzTVpMR2wyd3dVLUxLUWRuTU93WlBlTTlQeWNFY1V4VlF6MGV4SWs0alBVWXM4UjJCenJ5S1N6SGN3?oc=5",
     "src": "Forex Factory",
     "at": "24 Jul, 02:37"
    },
    {
     "title": "Trump says Saudi nuclear deal contingent on recognising Israel",
     "url": "https://news.google.com/rss/articles/CBMixAFBVV95cUxQUlp6YV9ySUNjMUVjdDlLWHNTcGVDeG40NkluUUE0Q2N4OURQRG5FZkhPWDVkNFB6aTRZZVhscE5RN3R4M3pucUd2UnQtZjloem5JLUZQOWJpZDdReEZPSWRfSXQybzdTd281bjNnUTZ2QkZ5RnNnZDJYcE9mWkxaWlJZTlVpX3M5VEpiVzJ3OEtPRXhPUlRMT1V6VzFleFp6WDYzOVl5MWZENzVtYnNaYWJKYzhwZjRpZVBMaWRvdmRhdFZL0gHLAUFVX3lxTE1MZlFsbDR5YjJaVDhSb3haU3psUVVjeTlaN1JxakcxRHNVYTlNT0gyb0ZUemhKeGhZSEpwSkpIMWlGbURfckg0Wi1RQllQbHFTWFgyYUFaTm1DNzhDMC0zSkZQb3RFeXpwOUxKaFJid2VwUzVmbGVFTFFWR3p4MGlxR094c3FYZ1B0MF9NTGlxTEZXQlN6dERuVE9QT1VIMVU0NDRBdVowcVNpMmJjT1FBQTZFSnZydWM4WWlBSVhBdlJTUnhOVHlSR2s4?oc=5",
     "src": "The Hindu",
     "at": "23 Jul, 18:15"
    },
    {
     "title": "U.S. slaps 10% tariffs on goods imported from India over issue of forced labour",
     "url": "https://news.google.com/rss/articles/CBMingFBVV95cUxQRk9kdjBHY3ptMEhaMkhXZWZkcVpmWUFNeS1xbjU0M3BOUmpUcGxfUEM0WVB1dHJETE16dmt1N2MtdEdsOVA0V2x4b1BmWHBBNjVqRjdFLUU1S01TN2RfMnNXMDF4NVlfdXJQUkVmQmhsWENIMnZzMDVLR0NjT3p1RmEwQVFBMVdES0NsSmFFbW5EMU9pclQzNzdYMy1nQQ?oc=5",
     "src": "The Hindu",
     "at": "24 Jul, 08:11"
    },
    {
     "title": "As oil soars, experts watch Red Sea tankers for clarity on Houthi blockade",
     "url": "https://news.google.com/rss/articles/CBMiuAFBVV95cUxQZHRWUzBiZTY0SGluMDR3YWwxWFR5RjFtR2dSS2dCd0p6TElfSmtMWVQxZm41Rjl4R0dDZlZONHM3RlF6NUNXVWFQdTBFNUhqalFpMEdLSnVJTk01Rk5ockpvdXYwblFXa0lKSUFGekRuNFBrZkJBOVh5RVlLZE12X0NrQlpmMVNnbUZzMV9MQzhFWGxZajZROWo5TnprbFJqaHlOWVdBblRvOXhGWWM5TU56Z3RMUVJI?oc=5",
     "src": "Al Jazeera",
     "at": "24 Jul, 09:05"
    },
    {
     "title": "'Baseless': India rejects Pakistan minister Ishaq Dar's remarks on Kashmir at ASEAN meet | India News",
     "url": "https://news.google.com/rss/articles/CBMi4AFBVV95cUxPQkRyUjV5MGMzZjJiUWpmcDlIUXIxTTNjTUVxVmQySnozbDJuNmM5b21rM2Iyc1d3LWZwdERHeXlKNm1SY0tId2h4M1I5dzlUMElFeUF4cGtvSXFYR3Y3OTB5ZjlKOHY3cWQ1YVRraEZOUnJXbzVfaVlKZzhsOUJ1VVJtMF92c0swbktwajFwTGxmcVVhRS1SX05XM25LVXIzRGJnTWNfSlNMT0h6VXdHTFhfUXNIWEZxaExCam1pYnk3dUFrZHVtQUpEWUVWU2FwcThuZjR0UHBmQW9kdjhZSdIB5gFBVV95cUxPU2d4M1A5eWZCZlp2ZlY5NmVwaC1JM1cyeS1TTkJ0ZDhLU1dmWk94cEZJUFFBVWVoMXBUSXljMzBzbWdCaTJ6WGJ3VzJER2NzUjRFX0pWSlJvWVdyb3NMUVdPeEZ4akVJNURGaTVYcEJJXzNPZnJhRzJlWU13Q1dTbGJmd21xcmpFaVpjUS1YRXFXQVROd0xBNFNCWWRpVmMwS0dnamhqS0NiZ293bW0yalZtTUliREt4bXRxODJ5OGc4aUdjNlVEX1I5bzh0eVRWR1dDa2RRWHgtNDdzcG44REo1djBhQQ?oc=5",
     "src": "Hindustan Times",
     "at": "23 Jul, 22:52"
    }
   ]
  },
  {
   "tag": "For You",
   "items": [
    {
     "title": "The 1.6x problem: Why India’s manufacturing AI spend is outrunning its data",
     "url": "https://news.google.com/rss/articles/CBMiwAFBVV95cUxNSDNmcGVFOTB5bFdXa3F4Tmk1Q1FVZ2twUzM5MnMtdmh0a09UNnNYd3c4MDlVODN2dUlZZmx2T2xadHJuRTlkN0FSMEdwUm04YkZsS3lIUThYYS1faXVtbG91UGJqaFRVZ25qaGVaOXVNdlVzelU1UzREXzNacGE5VEZab21BRkJ3ZXY2dTNmQXAzZjl3NDQwV1dUR1JGcV81eVFsUzZ2amsyUkxpOGoxemprQzhHdFVzUS1KdDR2XzI?oc=5",
     "src": "Express Computer",
     "at": "23 Jul, 16:05"
    },
    {
     "title": "AI-based Feed Intake Monitoring Market : Global Industry Analysis and Opportunity Assessment, 2036",
     "url": "https://news.google.com/rss/articles/CBMiiwFBVV95cUxPZW9QTnAzWHBJSWd5aGpLUkZyRUhPbEt3TjBRdjNzLWRxcmJPT1JheGVBMkJNTTA1dkZRcnlXcV9xcTVyV1NKWWxuR1B0dUpzTnEzaEdzOFpmUDRVVXdWTDlTdUdXT0pNaWh5aUJKSHlVaHhqbDNGNmg3aXhRS0trYndKbFU0Mms3YkQ4?oc=5",
     "src": "Future Market Insights",
     "at": "23 Jul, 19:02"
    },
    {
     "title": "The systems India builds today will define its economic future",
     "url": "https://news.google.com/rss/articles/CBMi4wFBVV95cUxOV1NtQnJsVkFOTnZnVWtxd2RvX0l6VUI2ZF9WS3ZOczJORzZSRUZ5ZkswbzlzRjlGX2ZvNEFES0JuMkhNLXpQbG50Q0syX0RNc05BRUtELW5LZWg5RjRPQzVsSGhjTXliem9zb1ZfZ3NWbWEyMlhkdWdvbFhpMVVqakMxM201eklEbk5iMFAxbjJWQXRwNUdKUGlvMHlkXzA1bWVNbkVLVHR6XzdXZjNNZG9nblRoN1ROUEpKcTdYTVh5SHFORlY2LWFhYlVsTjRtaTB5ZWV6Vm9OUVpHYlZzT3lwc9IB6AFBVV95cUxPb0NGUlVXV3VHNU5qQXJ1UHJvbHlaT0NjcFU0eERQYVZRYzYxbHNBY1ZCNFh3b1RtODRVQTl3UjVWWWU5dnNpLV9Ic2FMV0piSEJXdGxDaXl4cnBMcF9uWFd0N2F2cW92MEZPWWR6dFh0OXpTZFpQeHpUTGlJeS1mWmFmcVBneWNwdExWQjRZOGRpanExQ0VpNWZfMWFJWnVYR05EaVNjb2JNd3lqbmVuYU53SzB3MmpPUnlxald5ZFJ1ay1aVDdkWVpXY0JSTnpMalZySTN3MUNLamt2dWVpRjZWODRjWlg1?oc=5",
     "src": "ET CIO",
     "at": "23 Jul, 17:21"
    },
    {
     "title": "CGC University: Shaping The Next Generation - Where Learning Meets Career Success",
     "url": "https://news.google.com/rss/articles/CBMi0wFBVV95cUxOdFVvd3pDREhUVlJEMnVhMjUwQWF0WEYtOHFZMEdGQTU3bU1vSXByQzZnbzN0WHg3cE5nZGttOG5KVElnSW5tZ1ZIMTkwdHVVNGMtY0lOdEVWQWZNcEtVaXdNZ0VXbW1MLUdERHMtS29QTnJER3V3MzdOb1lvTC1HUDZNd2pGREFDSUpWMlVaVzl2T185ZkRZQ3VNWWcxM091VEMzNlotb0V2Q3lkU2ZJUEE0aEhYN3p5Qkp5a0laajFfclZtWVZEN1M4UnY1Xzg5VUJj0gHgAUFVX3lxTE1mSl9BektKc2g3aTBOazk3Y25QZzJQTjczVi1mMS12eFRCRE5XWmZXakZ1UHNlRDJOdmtpMXVPdkZaR0pYbEw0a1JJNS1YTEUwMDRyVUcxNUJJYVJ0aVA0X3BVOV80TG54dzF3ZlBhV0ZIZjdwdUs5QjNreFg2ZzJCVFJEWHBEVU1GaUpWRnZtZGNuNERyTG0xdDRHY25hYm0xMkFZUlczU3d6c2pDVDZmQWRRTXA5b0w0b1NzZEtVTFcxaXpINl9hNHo1ZGxudlVoY2NzWDZDN3gxTEFlNUc4?oc=5",
     "src": "Outlook India",
     "at": "24 Jul, 09:50"
    },
    {
     "title": "Asia Pacific Agriculture Gateway Market Size, Forecasts 2035",
     "url": "https://news.google.com/rss/articles/CBMijAFBVV95cUxPRkxsNnpnbnBNaWxrMEVjM2VSN1VZQnlMRUZaV1RpSzItMGNZVWNVN0lISzFmSEtzcmVhNHlST2hZb24wWGZ4a291bTRlUDk4Z21IRGhXSV92WldnNWxoaUktZHpUOTFYd3hScEtKc3BYRWczdGt2WGpWYTl4bjVWeXFnU1JEcnhjeEcwZg?oc=5",
     "src": "Global Market Insights Inc.",
     "at": "23 Jul, 11:01"
    },
    {
     "title": "AI Data Centre Leaders Map India’s Infrastructure Roadmap",
     "url": "https://news.google.com/rss/articles/CBMimwFBVV95cUxQMVpHTURJSmo1SUIxa3c2TjBvVEtubk5NWGpnNVNCM2RDeUJPcnpNd3lkNEh4ZnZLSUNTaFBKS2pNMWpVLWRINWR2VzJ3QzVZRG1MODdwbDlRUWwtU1lWSWlrWEIyOGxpbTRrMUFfejZMQ0FHdm1tR2cydU82NXg1UUR3NmpyYXBRT1l1YnlHNXhWQjdENTlFQWhGd9IBoAFBVV95cUxQNEhNUW1vNzJUXzVzN1otOWpmV1ZKYVgwX2xzcHRWTWtjcm1Jd0MxMjEzNm1XNzRDb3c2MndrNl9lT0NvanNZSnZlUnJzd1ZCVlBVVUdSeWVSRmUtbEt0MHJyRy1VT3FDTFdUU3lQRlNaRkM0ajctYUl6TDd3RnRrNktpUGJ0azhFSUFGTTFFSU55V0tNQWFzcGRZZi04SFRD?oc=5",
     "src": "TheWire.in",
     "at": "23 Jul, 17:52"
    }
   ]
  }
 ],
 "gk": [
  {
   "t": "Why there's an International Date Line",
   "teaser": "Cross it westward and you skip a day.",
   "more": "The Earth has 24 time zones; somewhere the calendar must flip. The line zigzags through the Pacific to avoid splitting countries. Fly Delhi to San Francisco and you can land at an earlier local time than you took off — the date line gives the day back."
  },
  {
   "t": "GST: one nation, one tax (2017)",
   "teaser": "It replaced a maze of central and state levies.",
   "more": "The Goods and Services Tax merged excise, VAT, service tax and more into one destination-based tax with slabs (0/5/12/18/28%). It made interstate commerce dramatically simpler — trucks no longer queue at state borders for tax checks — and every invoice feeds a single national IT backbone."
  },
  {
   "t": "ISRO's Chandrayaan-3 moment",
   "teaser": "In 2023 India became the first to land near the lunar south pole.",
   "more": "After Chandrayaan-2's lander crashed in 2019, ISRO's Vikram lander touched down softly on 23 August 2023 — making India the fourth country to soft-land on the Moon and the first at the south polar region, where ice deposits could support future missions. Mission cost: roughly ₹615 crore, less than many Hollywood films."
  },
  {
   "t": "ARPANET: the internet's grandfather",
   "teaser": "The first message in 1969 was meant to be 'LOGIN' — it crashed at 'LO'.",
   "more": "A US defence research network connecting four universities grew into the internet after TCP/IP became its common language in 1983. The web (websites, URLs, browsers) came later — invented by Tim Berners-Lee at CERN in 1989 as a layer on top of the internet."
  },
  {
   "t": "Moore's Law",
   "teaser": "Chip transistor counts doubled roughly every two years for 50 years.",
   "more": "Intel co-founder Gordon Moore's 1965 observation became the tech industry's metronome — it's why phones outpower old supercomputers. Physical limits have slowed it, which is partly why the industry pivoted to specialised chips (GPUs, AI accelerators) instead of just faster general processors."
  },
  {
   "t": "Why Silicon Valley is 'silicon'",
   "teaser": "The chip element, not the software.",
   "more": "The Santa Clara Valley earned the name in the 1970s from silicon semiconductor makers like Fairchild and Intel. Software, internet and AI giants came in later waves. Bengaluru earned the 'India's Silicon Valley' tag through the 1990s IT services boom — Infosys and Wipro, not chips."
  },
  {
   "t": "How vaccines work",
   "teaser": "A harmless preview teaches your immune system the enemy's face.",
   "more": "Vaccines present a dead, weakened, or fragment version of a pathogen (or, in mRNA vaccines, instructions to build one protein of it), so your body develops antibodies without the disease. Smallpox — which killed ~300 million people in the 20th century alone — became the first disease ever eradicated, in 1980."
  },
  {
   "t": "Plate tectonics built the Himalayas",
   "teaser": "India is still crashing into Asia at ~5 cm a year.",
   "more": "Around 50 million years ago the Indian plate slammed into the Eurasian plate; the crumple zone is the Himalayas, still rising a few millimetres yearly. The same collision makes the region earthquake-prone — the reason Delhi sits in seismic zone IV."
  },
  {
   "t": "Why the sky is blue",
   "teaser": "Air scatters blue light more than red.",
   "more": "Sunlight contains all colours; molecules in the atmosphere scatter shorter (bluer) wavelengths far more — called Rayleigh scattering. At sunset, light travels through more air, the blue scatters away before reaching you, leaving reds and oranges."
  },
  {
   "t": "Black holes, minus the mystery",
   "teaser": "Gravity so strong that light can't leave.",
   "more": "When a massive star collapses, its gravity can warp space so severely nothing escapes past the 'event horizon'. They're detected by their effect on nearby matter. The first-ever photo of one (M87*, 2019) took a telescope network the size of Earth."
  }
 ],
 "gkMore": [
  {
   "t": "The Great Wall of China isn't visible from space",
   "teaser": "The naked-eye claim is a stubborn myth.",
   "more": "Contrary to popular belief, the Great Wall cannot be seen from space with the unaided eye — it is very long but only a few metres wide, blending into the surrounding terrain. Astronauts have confirmed they cannot pick it out from orbit without help. City lights and airport runways are far easier to spot from the International Space Station."
  },
  {
   "t": "The Sahara is nearly the size of the United States",
   "teaser": "The world's largest hot desert.",
   "more": "The Sahara covers about 9 million square kilometres, roughly the area of the United States or China. Yet it is not the biggest desert overall — Antarctica, a frozen desert, is larger. The Sahara was green with lakes and grassland just a few thousand years ago, and will likely turn green again as Earth's orbit slowly shifts."
  },
  {
   "t": "Sunlight takes about eight minutes to reach Earth",
   "teaser": "You always see the Sun as it was, never as it is.",
   "more": "Light travels at about 300,000 kilometres per second, but the Sun is so distant that its light takes roughly 8 minutes and 20 seconds to arrive. If the Sun vanished, we would keep seeing and feeling it for those eight minutes. Light from the next-nearest star takes over four years to reach us."
  },
  {
   "t": "You are literally made of stardust",
   "teaser": "The atoms in your body were forged inside stars.",
   "more": "Almost every element heavier than hydrogen — the carbon in your cells, the oxygen you breathe, the iron in your blood — was created inside stars and flung out when they died. Those atoms drifted through space, gathered to form our Sun and planets, and eventually became you. As astronomer Carl Sagan put it, we are 'star stuff.'"
  },
  {
   "t": "Tiny 'water bears' can survive the vacuum of space",
   "teaser": "Nearly indestructible microscopic animals.",
   "more": "Tardigrades, or water bears, are half-millimetre creatures that can endure being boiled, frozen near absolute zero, dried out for years, and even exposed to the vacuum and radiation of open space. They manage it by curling into a shrivelled, near-dead state called cryptobiosis. Scientists have revived specimens after decades in deep freeze."
  },
  {
   "t": "Most global trade is still priced in US dollars",
   "teaser": "A legacy of a deal struck in 1944.",
   "more": "After World War II, the 1944 Bretton Woods agreement pegged major currencies to the US dollar, which was itself convertible to gold. Even after that gold link ended in 1971, the dollar remained the world's dominant reserve and trade currency, especially for oil — the so-called petrodollar. This gives the US enormous financial leverage, which rivals increasingly try to reduce."
  },
  {
   "t": "The Rule of 72 tells you when your money doubles",
   "teaser": "Just divide 72 by the interest rate.",
   "more": "Compound interest means you earn returns on your past returns, so money snowballs over time. A handy shortcut, the Rule of 72, estimates how long an investment takes to double: divide 72 by the annual return. At 8% a year, money doubles in about nine years — which is why starting early beats investing large sums late."
  },
  {
   "t": "The first webcam was invented to watch a coffee pot",
   "teaser": "Cambridge scientists were tired of empty pots.",
   "more": "In 1991, researchers at Cambridge University pointed a camera at a coffee pot so they could check from their desks whether it was full before walking over. Connected to the web in 1993, it became the world's first webcam. The famous 'Trojan Room coffee pot' was switched off in 2001 and auctioned online."
  },
  {
   "t": "The QWERTY keyboard was built to prevent jams",
   "teaser": "It deliberately separates the letters you type together.",
   "more": "The QWERTY layout was designed in the 1870s for mechanical typewriters, spacing common letter pairs far apart so the metal typebars were less likely to clash and jam. When typewriters gave way to computers, the mechanical reason disappeared, but the layout was far too entrenched to replace. Faster designs like Dvorak exist, but never caught on."
  },
  {
   "t": "The Kumbh Mela is the largest human gathering on Earth",
   "teaser": "Tens of millions converge at India's sacred rivers.",
   "more": "The Hindu Kumbh Mela, held on a rotating cycle at sites like Prayagraj, draws the biggest crowds of people anywhere on the planet. On peak days tens of millions bathe at the river confluence, and the temporary tent city grows so vast it shows up clearly in satellite images. UNESCO recognises it as intangible cultural heritage of humanity."
  }
 ],
 "learn": [
  {
   "title": "What happens when you load a web page",
   "teaser": "The elegant plumbing beneath every click.",
   "body": [
    "When you type an address and hit enter, your request does not travel as one continuous stream. Instead, the data is broken into small chunks called packets, each individually addressed and sent off across the network. Guided by a family of rules known as TCP/IP, these packets hop from router to router — often taking different paths — and are reassembled in the correct order at the destination. There is no central controller directing traffic; the system is deliberately decentralised.",
    "Two pieces of infrastructure make this feel instant. The Domain Name System (DNS) acts like the internet's phone book, translating a human-friendly name like a website's address into the numerical IP address computers actually use to find each other. And most intercontinental traffic does not go by satellite but through a web of fibre-optic cables lying on the ocean floor, carrying data between continents at nearly the speed of light.",
    "This architecture is a direct inheritance from the internet's origins in ARPANET, which was designed so that data could reroute around damaged nodes and keep flowing. That resilience is why the network scales so gracefully and rarely goes fully dark. Every web page you open is the product of thousands of these tiny packets racing across the planet and back, usually in a fraction of a second."
   ]
  },
  {
   "title": "The AI shift: what large language models actually do",
   "teaser": "Powerful pattern machines, not digital minds.",
   "body": [
    "The recent wave of artificial intelligence is driven by large language models (LLMs) — the technology behind modern AI chatbots. At their core, these systems are trained on vast quantities of text and learn to do something deceptively simple: predict the next word in a sequence. By doing this billions of times over enormous datasets, they absorb the statistical patterns of language, along with a great deal of the knowledge encoded in that text, and can then generate fluent, often strikingly useful responses.",
    "It helps to be clear about what this is and isn't. An LLM does not 'understand' the world the way a person does, nor does it look up facts in a database. It generates plausible continuations based on patterns, which is why it can be articulate and helpful but also confidently wrong — producing 'hallucinations,' or inheriting biases present in its training data. The breakthrough that made today's models possible was a neural-network design called the transformer, introduced in 2017, combined with vast computing power.",
    "The economic and social implications are still unfolding. AI is already reshaping how people write, code, research and create, and it poses particular questions for economies like India's, with its large services and IT sector. The realistic near-term picture is less science-fiction robot and more a powerful general-purpose tool — one that amplifies human work, demands new skills, and requires care about accuracy, fairness and appropriate use."
   ]
  },
  {
   "title": "Why tiny chips decide global power",
   "teaser": "The most important industry most people never think about.",
   "body": [
    "Semiconductors — the microchips inside phones, cars, appliances, weapons and data centres — have become the foundation of the modern economy. What makes them geopolitically explosive is how extraordinarily concentrated their production is. The most advanced chips are manufactured by a handful of firms, above all Taiwan's TSMC, and the ultra-precise machines needed to etch them are made by essentially one company, ASML in the Netherlands, while much of the cutting-edge design comes from the United States.",
    "This means no single country can make a leading-edge chip alone; the supply chain is a globally intertwined web with critical choke points. That fragility became painfully visible during the shortages of 2021, when a shortfall of chips idled car factories worldwide. It has also turned semiconductors into a central front in the rivalry between the United States and China, with export controls on advanced chips and chipmaking equipment used as tools of statecraft.",
    "Taiwan's dominance in particular gives the island outsized strategic importance and adds a dangerous edge to tensions over its status. Governments have responded by pouring money into building domestic chip factories, or 'fabs,' to reduce their dependence — including India, which is courting fabrication and assembly plants as part of its push to become a manufacturing hub. In the coming decades, who makes the world's chips may matter as much as who controls its oil once did."
   ]
  },
  {
   "title": "P/E ratio: the market's price tag",
   "teaser": "How many years of profit you're paying for one share.",
   "body": [
    "Price-to-Earnings = share price ÷ earnings per share. A P/E of 25 means you pay ₹25 for every ₹1 of annual profit. High P/E signals the market expects fast growth (or the stock is expensive); low P/E signals slow growth expectations (or a bargain).",
    "It's only meaningful against context: the company's own history, its sector average, and growth rate. Indian IT often trades at 20–30; PSU banks far lower. A 'cheap' stock with shrinking profits is usually cheap for a reason."
   ]
  },
  {
   "title": "Correlation is not causation",
   "teaser": "The most important sentence in analytics.",
   "body": [
    "Ice cream sales and drownings rise together — summer causes both. When two metrics move together, there are always four possibilities: A causes B, B causes A, something else causes both, or coincidence. Dashboards show correlation; only controlled experiments or careful causal analysis show causation.",
    "Practical BI reflex: before reporting 'X drove Y', ask what else changed in the same window — a campaign, a price change, seasonality, a tracking change. The last one bites analysts most often."
   ]
  },
  {
   "title": "Mean vs median: which lies less?",
   "teaser": "One billionaire in a room makes the 'average' person rich.",
   "body": [
    "The mean (sum ÷ count) is dragged by outliers; the median (middle value) isn't. Average income sounds impressive when a few earn crores; median income tells you what the typical person makes. Same for ticket sizes, session times, order values.",
    "Rule of thumb: for skewed data (money, wait times, engagement), report the median or percentiles. If mean and median differ a lot, that gap itself is a finding — your distribution has a long tail worth investigating."
   ]
  },
  {
   "title": "Opportunity cost",
   "teaser": "The real cost of anything is what you gave up to get it.",
   "body": [
    "Spending ₹15 lakh on a car isn't just ₹15 lakh — it's also the ~₹47 lakh that money could become in 10 years at 12%. Every choice of time or money silently declines the alternatives. Economists call the best foregone alternative the opportunity cost.",
    "It reframes decisions: a 'free' three-hour meeting costs the work you'd have shipped. An okay job offer costs the better one you stopped searching for. Comparing against 'doing nothing' is almost always the wrong baseline."
   ]
  },
  {
   "title": "How IPOs actually work",
   "teaser": "A private company sells shares to the public for the first time.",
   "body": [
    "The company hires investment banks to set a price band, files a prospectus (DRHP) with SEBI, and collects bids. Retail investors apply in lots; oversubscribed issues allot by lottery. On listing day the stock starts trading — sometimes far above or below issue price.",
    "Listing 'pops' make headlines, but the base rate is sobering: many hyped IPOs trade below issue price within a year (India's 2021 tech-IPO batch is the classic case). Reading where the money goes — fresh growth capital vs early investors cashing out — tells you a lot."
   ]
  }
 ]
}